Workbook

Sheet IPO_2023_05_04
A1: Snapshot Date | B1: 2023-05-04
A2: Use same date for Date + Effective Date in all formulas
A4: Identifier | B4: Company | C4: Revenue TTM | D4: Shares Outstanding | E4: Net Debt | F4: EBITDA TTM | G4: EBITDA NTM | H4: Diluted EPS | I4: Market Cap | J4: Enterprise Value | K4: EV/LTM | L4: EV/NTM | M4: P/NTM
A5: NYS:KVUE | B5: Kenvue | C5: =_xll.PBF(A5,"Total Revenue","TTM",$B$1,"","USD","",$B$1) -> 14950000000 | D5: =_xll.PBF(A5,"Diluted Weighted Average Shares Outstanding","TTM",$B$1,"","USD","",$B$1) -> 1888972560 | E5: =_xll.PBF(A5,"Net Debt","TTM",$B$1,"","USD","",$B$1) -> -1115000000 | F5: =_xll.PBF(A5,"EBITDA","TTM",$B$1,"","USD","",$B$1) -> 3281000000 | G5: =_xll.PBF(A5,"EBITDA","NTM",$B$1,"","USD","",$B$1) -> 3281000000 | H5: =_xll.PBF(A5,"Diluted EPS (Analyst Normalized)","NTM",$B$1,"","USD","",$B$1) -> 0.93 | I5: =D16*D5 -> 50813361864 | J5: =I5+E5 -> 49698361864 | K5: =IFERROR(J5/F5,"") -> 15.147322 | L5: =IFERROR(J5/G5,"") -> 15.147322 | M5: =I5/(D5*H5) -> 28.924731
A6: NYS:PG | B6: Procter & Gamble | C6: =_xll.PBF(A6,"Total Revenue","TTM",$B$1,"","USD","",$B$1) -> 80968000000 | D6: =_xll.PBF(A6,"Diluted Weighted Average Shares Outstanding","TTM",$B$1,"","USD","",$B$1) -> 2495300000 | E6: =_xll.PBF(A6,"Net Debt","TTM",$B$1,"","USD","",$B$1) -> 28995000000 | F6: =_xll.PBF(A6,"EBITDA","TTM",$B$1,"","USD","",$B$1) -> 20919000000 | G6: =_xll.PBF(A6,"EBITDA","NTM",$B$1,"","USD","",$B$1) -> 20919000000 | H6: =_xll.PBF(A6,"Diluted EPS (Analyst Normalized)","NTM",$B$1,"","USD","",$B$1) -> 5.74 | I6: =D17*D6 -> 388044103000 | J6: =I6+E6 -> 417039103000 | K6: =IFERROR(J6/F6,"") -> 19.935901 | L6: =IFERROR(J6/G6,"") -> 19.935901 | M6: =I6/(D6*H6) -> 27.092334
A7: NAS:KMB | B7: Kimberly-Clark | C7: =_xll.PBF(A7,"Total Revenue","TTM",$B$1,"","USD","",$B$1) -> 20275000000 | D7: =_xll.PBF(A7,"Diluted Weighted Average Shares Outstanding","TTM",$B$1,"","USD","",$B$1) -> 338400000 | E7: =_xll.PBF(A7,"Net Debt","TTM",$B$1,"","USD","",$B$1) -> 7957000000 | F7: =_xll.PBF(A7,"EBITDA","TTM",$B$1,"","USD","",$B$1) -> 3444000000 | G7: =_xll.PBF(A7,"EBITDA","NTM",$B$1,"","USD","",$B$1) -> 3444000000 | H7: =_xll.PBF(A7,"Diluted EPS (Analyst Normalized)","NTM",$B$1,"","USD","",$B$1) -> 5.84 | I7: =D18*D7 -> 48868344000 | J7: =I7+E7 -> 56825344000 | K7: =IFERROR(J7/F7,"") -> 16.49981 | L7: =IFERROR(J7/G7,"") -> 16.49981 | M7: =I7/(D7*H7) -> 24.72774
A8: NYS:CL | B8: Colgate-Palmolive | C8: =_xll.PBF(A8,"Total Revenue","TTM",$B$1,"","USD","",$B$1) -> 18338000000 | D8: =_xll.PBF(A8,"Diluted Weighted Average Shares Outstanding","TTM",$B$1,"","USD","",$B$1) -> 836125000 | E8: =_xll.PBF(A8,"Net Debt","TTM",$B$1,"","USD","",$B$1) -> 8040000000 | F8: =_xll.PBF(A8,"EBITDA","TTM",$B$1,"","USD","",$B$1) -> 3141000000 | G8: =_xll.PBF(A8,"EBITDA","NTM",$B$1,"","USD","",$B$1) -> 3141000000 | H8: =_xll.PBF(A8,"Diluted EPS (Analyst Normalized)","NTM",$B$1,"","USD","",$B$1) -> 1.92 | I8: =D19*D8 -> 6.7550539e+10 | J8: =I8+E8 -> 75590538750 | K8: =IFERROR(J8/F8,"") -> 24.065756 | L8: =IFERROR(J8/G8,"") -> 24.065756 | M8: =I8/(D8*H8) -> 42.078125
A9: NYS:CHD | B9: Church & Dwight | C9: =_xll.PBF(A9,"Total Revenue","TTM",$B$1,"","USD","",$B$1) -> 5508200000 | D9: =_xll.PBF(A9,"Diluted Weighted Average Shares Outstanding","TTM",$B$1,"","USD","",$B$1) -> 246325000 | E9: =_xll.PBF(A9,"Net Debt","TTM",$B$1,"","USD","",$B$1) -> 2216000000 | F9: =_xll.PBF(A9,"EBITDA","TTM",$B$1,"","USD","",$B$1) -> 844100000 | G9: =_xll.PBF(A9,"EBITDA","NTM",$B$1,"","USD","",$B$1) -> 844100000 | H9: =_xll.PBF(A9,"Diluted EPS (Analyst Normalized)","NTM",$B$1,"","USD","",$B$1) -> 1.67 | I9: =D20*D9 -> 24056099500 | J9: =I9+E9 -> 26272099500 | K9: =IFERROR(J9/F9,"") -> 31.124392 | L9: =IFERROR(J9/G9,"") -> 31.124392 | M9: =I9/(D9*H9) -> 58.479042
A10: NYS:ABT | B10: Abbott Laboratories | C10: =_xll.PBF(A10,"Total Revenue","TTM",$B$1,"","USD","",$B$1) -> 41505000000 | D10: =_xll.PBF(A10,"Diluted Weighted Average Shares Outstanding","TTM",$B$1,"","USD","",$B$1) -> 1758293250 | E10: =_xll.PBF(A10,"Net Debt","TTM",$B$1,"","USD","",$B$1) -> 7368000000 | F10: =_xll.PBF(A10,"EBITDA","TTM",$B$1,"","USD","",$B$1) -> 10552000000 | G10: =_xll.PBF(A10,"EBITDA","NTM",$B$1,"","USD","",$B$1) -> 10552000000 | H10: =_xll.PBF(A10,"Diluted EPS (Analyst Normalized)","NTM",$B$1,"","USD","",$B$1) -> 3.29 | I10: =_xll.PBF(A10,"Market Cap","TTM",$B$1,"","USD","",$B$1) -> 192779642137 | J10: =I10+E10 -> 200147642137 | K10: =IFERROR(J10/F10,"") -> 18.967745 | L10: =IFERROR(J10/G10,"") -> 18.967745 | M10: =I10/(D10*H10) -> 33.325292
A11: NYS:COTY | B11: Coty | C11: =_xll.PBF(A11,"Total Revenue","TTM",$B$1,"","USD","",$B$1) -> 5268100000 | D11: =_xll.PBF(A11,"Diluted Weighted Average Shares Outstanding","TTM",$B$1,"","USD","",$B$1) -> 868800000 | E11: =_xll.PBF(A11,"Net Debt","TTM",$B$1,"","USD","",$B$1) -> 4127500000 | F11: =_xll.PBF(A11,"EBITDA","TTM",$B$1,"","USD","",$B$1) -> 941400000 | G11: =_xll.PBF(A11,"EBITDA","NTM",$B$1,"","USD","",$B$1) -> 941400000 | H11: =_xll.PBF(A11,"Diluted EPS (Analyst Normalized)","NTM",$B$1,"","USD","",$B$1) -> 0.14 | I11: =_xll.PBF(A11,"Market Cap","TTM",$B$1,"","USD","",$B$1) -> 9949793231 | J11: =I11+E11 -> 14077293231 | K11: =IFERROR(J11/F11,"") -> 14.953573 | L11: =IFERROR(J11/G11,"") -> 14.953573 | M11: =I11/(D11*H11) -> 81.802431
A12: NYS:EPC | B12: Edgewell Personal Care | C12: =_xll.PBF(A12,"Total Revenue","TTM",$B$1,"","USD","",$B$1) -> 2177500000 | D12: =_xll.PBF(A12,"Diluted Weighted Average Shares Outstanding","TTM",$B$1,"","USD","",$B$1) -> 52825000 | E12: =_xll.PBF(A12,"Net Debt","TTM",$B$1,"","USD","",$B$1) -> 1383500000 | F12: =_xll.PBF(A12,"EBITDA","TTM",$B$1,"","USD","",$B$1) -> 289900000 | G12: =_xll.PBF(A12,"EBITDA","NTM",$B$1,"","USD","",$B$1) -> 289900000 | H12: =_xll.PBF(A12,"Diluted EPS (Analyst Normalized)","NTM",$B$1,"","USD","",$B$1) -> 1.88 | I12: =_xll.PBF(A12,"Market Cap","TTM",$B$1,"","USD","",$B$1) -> 2221222392 | J12: =I12+E12 -> 3604722392 | K12: =IFERROR(J12/F12,"") -> 12.434365 | L12: =IFERROR(J12/G12,"") -> 12.434365 | M12: =I12/(D12*H12) -> 22.366328
D16: {=_xlfn.STOCKHISTORY("KVUE",$B$1,$B$1,0,0,1)} -> 26.9
D17: {=_xlfn.STOCKHISTORY("PG",$B$1,$B$1,0,0,1)} -> 155.51
D18: {=_xlfn.STOCKHISTORY("KMB",$B$1,$B$1,0,0,1)} -> 144.41
D19: {=_xlfn.STOCKHISTORY("CL",$B$1,$B$1,0,0,1)} -> 80.79
D20: {=_xlfn.STOCKHISTORY("CHD",$B$1,$B$1,0,0,1)} -> 97.66

Sheet Post1Y_2024_05_04
A1: Snapshot Date | B1: 2024-05-04
A2: Use same date for Date + Effective Date in all formulas
A4: Identifier | B4: Company | C4: Revenue TTM | D4: Shares Outstanding | E4: Net Debt | F4: EBITDA TTM | G4: EBITDA NTM | H4: Diluted EPS (Analyst Normalized) | I4: Market Cap | J4: Enterprise Value | K4: EV/LTM | L4: EV/NTM | M4: P/NTM
A5: NYS:KVUE | B5: Kenvue | C5: =_xll.PBF(A5,"Total Revenue","TTM",$B$1,"","USD","",$B$1) -> 15444000000 | D5: =_xll.PBF(A5,"Diluted Weighted Average Shares Outstanding","TTM",$B$1,"","USD","",$B$1) -> 1850000000 | E5: =_xll.PBF(A5,"Net Debt","TTM",$B$1,"","USD","",$B$1) -> 7045000000 | F5: =_xll.PBF(A5,"EBITDA","TTM",$B$1,"","USD","",$B$1) -> 3067000000 | G5: =_xll.PBF(A5,"EBITDA","NTM",$B$1,"","USD","",$B$1) -> 3067000000 | H5: =_xll.PBF(A5,"Diluted EPS (Analyst Normalized)","NTM",$B$1,"","USD","",$B$1) -> 0.9 | I5: =D16*D5 -> 35520000000 | J5: =I5+E5 -> 42565000000 | K5: =IFERROR(J5/F5,"") -> 13.878383 | L5: =IFERROR(J5/G5,"") -> 13.878383 | M5: =I5/(D5*H5) -> 21.333333
A6: NYS:PG | B6: Procter & Gamble | C6: =_xll.PBF(A6,"Total Revenue","TTM",$B$1,"","USD","",$B$1) -> 84060000000 | D6: =_xll.PBF(A6,"Diluted Weighted Average Shares Outstanding","TTM",$B$1,"","USD","",$B$1) -> 2473250000 | E6: =_xll.PBF(A6,"Net Debt","TTM",$B$1,"","USD","",$B$1) -> 25154000000 | F6: =_xll.PBF(A6,"EBITDA","TTM",$B$1,"","USD","",$B$1) -> 22428000000 | G6: =_xll.PBF(A6,"EBITDA","NTM",$B$1,"","USD","",$B$1) -> 22428000000 | H6: =_xll.PBF(A6,"Diluted EPS (Analyst Normalized)","NTM",$B$1,"","USD","",$B$1) -> 6.12 | I6: =D17*D6 -> 406750695000 | J6: =I6+E6 -> 431904695000 | K6: =IFERROR(J6/F6,"") -> 19.257388 | L6: =IFERROR(J6/G6,"") -> 19.257388 | M6: =I6/(D6*H6) -> 26.872549
A7: NAS:KMB | B7: Kimberly-Clark | C7: =_xll.PBF(A7,"Total Revenue","TTM",$B$1,"","USD","",$B$1) -> 17100000000 | D7: =_xll.PBF(A7,"Diluted Weighted Average Shares Outstanding","TTM",$B$1,"","USD","",$B$1) -> 338725000 | E7: =_xll.PBF(A7,"Net Debt","TTM",$B$1,"","USD","",$B$1) -> 7117000000 | F7: =_xll.PBF(A7,"EBITDA","TTM",$B$1,"","USD","",$B$1) -> 2650000000 | G7: =_xll.PBF(A7,"EBITDA","NTM",$B$1,"","USD","",$B$1) -> 2650000000 | H7: =_xll.PBF(A7,"Diluted EPS (Analyst Normalized)","NTM",$B$1,"","USD","",$B$1) -> 5.44 | I7: =D18*D7 -> 46097085250 | J7: =I7+E7 -> 53214085250 | K7: =IFERROR(J7/F7,"") -> 20.080787 | L7: =IFERROR(J7/G7,"") -> 20.080787 | M7: =I7/(D7*H7) -> 25.016544
A8: NYS:CL | B8: Colgate-Palmolive | C8: =_xll.PBF(A8,"Total Revenue","TTM",$B$1,"","USD","",$B$1) -> 19752000000 | D8: =_xll.PBF(A8,"Diluted Weighted Average Shares Outstanding","TTM",$B$1,"","USD","",$B$1) -> 827425000 | E8: =_xll.PBF(A8,"Net Debt","TTM",$B$1,"","USD","",$B$1) -> 7610000000 | F8: =_xll.PBF(A8,"EBITDA","TTM",$B$1,"","USD","",$B$1) -> 4623000000 | G8: =_xll.PBF(A8,"EBITDA","NTM",$B$1,"","USD","",$B$1) -> 4623000000 | H8: =_xll.PBF(A8,"Diluted EPS (Analyst Normalized)","NTM",$B$1,"","USD","",$B$1) -> 3.16 | I8: =D19*D8 -> 76851234000 | J8: =I8+E8 -> 84461234000 | K8: =IFERROR(J8/F8,"") -> 18.269789 | L8: =IFERROR(J8/G8,"") -> 18.269789 | M8: =I8/(D8*H8) -> 29.392405
A9: NYS:CHD | B9: Church & Dwight | C9: =_xll.PBF(A9,"Total Revenue","TTM",$B$1,"","USD","",$B$1) -> 5941400000 | D9: =_xll.PBF(A9,"Diluted Weighted Average Shares Outstanding","TTM",$B$1,"","USD","",$B$1) -> 247425000 | E9: =_xll.PBF(A9,"Net Debt","TTM",$B$1,"","USD","",$B$1) -> 1857100000 | F9: =_xll.PBF(A9,"EBITDA","TTM",$B$1,"","USD","",$B$1) -> 1304000000 | G9: =_xll.PBF(A9,"EBITDA","NTM",$B$1,"","USD","",$B$1) -> 1304000000 | H9: =_xll.PBF(A9,"Diluted EPS (Analyst Normalized)","NTM",$B$1,"","USD","",$B$1) -> 3.15 | I9: =D20*D9 -> 26254266750 | J9: =I9+E9 -> 28111366750 | K9: =IFERROR(J9/F9,"") -> 21.557797 | L9: =IFERROR(J9/G9,"") -> 21.557797 | M9: =I9/(D9*H9) -> 33.685714
A10: NYS:ABT | B10: Abbott Laboratories | C10: =_xll.PBF(A10,"Total Revenue","TTM",$B$1,"","USD","",$B$1) -> 40326000000 | D10: =_xll.PBF(A10,"Diluted Weighted Average Shares Outstanding","TTM",$B$1,"","USD","",$B$1) -> 1748484250 | E10: =_xll.PBF(A10,"Net Debt","TTM",$B$1,"","USD","",$B$1) -> 7935000000 | F10: =_xll.PBF(A10,"EBITDA","TTM",$B$1,"","USD","",$B$1) -> 10041000000 | G10: =_xll.PBF(A10,"EBITDA","NTM",$B$1,"","USD","",$B$1) -> 10041000000 | H10: =_xll.PBF(A10,"Diluted EPS (Analyst Normalized)","NTM",$B$1,"","USD","",$B$1) -> 3.21 | I10: =_xll.PBF(A10,"Market Cap","TTM",$B$1,"","USD","",$B$1) -> 184227215078 | J10: =I10+E10 -> 192162215078 | K10: =IFERROR(J10/F10,"") -> 19.137757 | L10: =IFERROR(J10/G10,"") -> 19.137757 | M10: =I10/(D10*H10) -> 32.823662
A11: NYS:COTY | B11: Coty | C11: =_xll.PBF(A11,"Total Revenue","TTM",$B$1,"","USD","",$B$1) -> 6009500000 | D11: =_xll.PBF(A11,"Diluted Weighted Average Shares Outstanding","TTM",$B$1,"","USD","",$B$1) -> 885900000 | E11: =_xll.PBF(A11,"Net Debt","TTM",$B$1,"","USD","",$B$1) -> 3554900000 | F11: =_xll.PBF(A11,"EBITDA","TTM",$B$1,"","USD","",$B$1) -> 1209600000 | G11: =_xll.PBF(A11,"EBITDA","NTM",$B$1,"","USD","",$B$1) -> 1209600000 | H11: =_xll.PBF(A11,"Diluted EPS (Analyst Normalized)","NTM",$B$1,"","USD","",$B$1) -> 0.35 | I11: =_xll.PBF(A11,"Market Cap","TTM",$B$1,"","USD","",$B$1) -> 10383959031 | J11: =I11+E11 -> 13938859031 | K11: =IFERROR(J11/F11,"") -> 11.523528 | L11: =IFERROR(J11/G11,"") -> 11.523528 | M11: =I11/(D11*H11) -> 33.48962
A12: NYS:EPC | B12: Edgewell Personal Care | C12: =_xll.PBF(A12,"Total Revenue","TTM",$B$1,"","USD","",$B$1) -> 2271400000 | D12: =_xll.PBF(A12,"Diluted Weighted Average Shares Outstanding","TTM",$B$1,"","USD","",$B$1) -> 51450000 | E12: =_xll.PBF(A12,"Net Debt","TTM",$B$1,"","USD","",$B$1) -> 1262300000 | F12: =_xll.PBF(A12,"EBITDA","TTM",$B$1,"","USD","",$B$1) -> 306500000 | G12: =_xll.PBF(A12,"EBITDA","NTM",$B$1,"","USD","",$B$1) -> 306500000 | H12: =_xll.PBF(A12,"Diluted EPS (Analyst Normalized)","NTM",$B$1,"","USD","",$B$1) -> 2.06 | I12: =_xll.PBF(A12,"Market Cap","TTM",$B$1,"","USD","",$B$1) -> 1888470485 | J12: =I12+E12 -> 3150770485 | K12: =IFERROR(J12/F12,"") -> 10.279838 | L12: =IFERROR(J12/G12,"") -> 10.279838 | M12: =I12/(D12*H12) -> 17.817945
D16: {=_xlfn.STOCKHISTORY("KVUE",$B$1-1,$B$1,0,0,1)} -> 19.2
D17: {=_xlfn.STOCKHISTORY("PG",$B$1-1,$B$1,0,0,1)} -> 164.46
D18: {=_xlfn.STOCKHISTORY("KMB",$B$1-1,$B$1,0,0,1)} -> 136.09
D19: {=_xlfn.STOCKHISTORY("CL",$B$1-1,$B$1,0,0,1)} -> 92.88
D20: {=_xlfn.STOCKHISTORY("CHD",$B$1-1,$B$1,0,0,1)} -> 106.11

Sheet PreDeal_2025_10_31
A1: Snapshot Date | B1: 2025-10-31
A2: Use same date for Date + Effective Date in all formulas
A4: Identifier | B4: Company | C4: Revenue TTM | D4: Shares Outstanding | E4: Net Debt | F4: EBITDA TTM | G4: EBITDA NTM | H4: Diluted EPS (Analyst Normalized) | I4: Market Cap | J4: Enterprise Value | K4: EV/LTM | L4: EV/NTM | M4: P/NTM
A5: NYS:KVUE | B5: Kenvue | C5: =_xll.PBF(A5,"Total Revenue","TTM",$B$1,"","USD","",$B$1) -> 15141000000 | D5: =_xll.PBF(A5,"Diluted Weighted Average Shares Outstanding","TTM",$B$1,"","USD","",$B$1) -> 1926500000 | E5: =_xll.PBF(A5,"Net Debt","TTM",$B$1,"","USD","",$B$1) -> 7674000000 | F5: =_xll.PBF(A5,"EBITDA","TTM",$B$1,"","USD","",$B$1) -> 2958000000 | G5: =_xll.PBF(A5,"EBITDA","NTM",$B$1,"","USD","",$B$1) -> 2958000000 | H5: =_xll.PBF(A5,"Diluted EPS (Analyst Normalized)","NTM",$B$1,"","USD","",$B$1) -> 0.74 | I5: =G15*D5 -> 27683805000 | J5: =I5+E5 -> 35357805000 | K5: =IFERROR(J5/F5,"") -> 11.953281 | L5: =IFERROR(J5/G5,"") -> 11.953281 | M5: =I5/(D5*H5) -> 19.418919
A6: NYS:PG | B6: Procter & Gamble | C6: =_xll.PBF(A6,"Total Revenue","TTM",$B$1,"","USD","",$B$1) -> 84933000000 | D6: =_xll.PBF(A6,"Diluted Weighted Average Shares Outstanding","TTM",$B$1,"","USD","",$B$1) -> 2447100000 | E6: =_xll.PBF(A6,"Net Debt","TTM",$B$1,"","USD","",$B$1) -> 24775000000 | F6: =_xll.PBF(A6,"EBITDA","TTM",$B$1,"","USD","",$B$1) -> 24365000000 | G6: =_xll.PBF(A6,"EBITDA","NTM",$B$1,"","USD","",$B$1) -> 24365000000 | H6: =_xll.PBF(A6,"Diluted EPS (Analyst Normalized)","NTM",$B$1,"","USD","",$B$1) -> 6.85 | I6: =G16*D6 -> 367970427000 | J6: =I6+E6 -> 392745427000 | K6: =IFERROR(J6/F6,"") -> 16.119246 | L6: =IFERROR(J6/G6,"") -> 16.119246 | M6: =I6/(D6*H6) -> 21.951825
A7: NAS:KMB | B7: Kimberly-Clark | C7: =_xll.PBF(A7,"Total Revenue","TTM",$B$1,"","USD","",$B$1) -> 16471000000 | D7: =_xll.PBF(A7,"Diluted Weighted Average Shares Outstanding","TTM",$B$1,"","USD","",$B$1) -> 333475000 | E7: =_xll.PBF(A7,"Net Debt","TTM",$B$1,"","USD","",$B$1) -> 6687000000 | F7: =_xll.PBF(A7,"EBITDA","TTM",$B$1,"","USD","",$B$1) -> 3032000000 | G7: =_xll.PBF(A7,"EBITDA","NTM",$B$1,"","USD","",$B$1) -> 3032000000 | H7: =_xll.PBF(A7,"Diluted EPS (Analyst Normalized)","NTM",$B$1,"","USD","",$B$1) -> 5.91 | I7: =G17*D7 -> 39920292250 | J7: =I7+E7 -> 46607292250 | K7: =IFERROR(J7/F7,"") -> 15.371798 | L7: =IFERROR(J7/G7,"") -> 15.371798 | M7: =I7/(D7*H7) -> 20.255499
A8: NYS:CL | B8: Colgate-Palmolive | C8: =_xll.PBF(A8,"Total Revenue","TTM",$B$1,"","USD","",$B$1) -> 20097000000 | D8: =_xll.PBF(A8,"Diluted Weighted Average Shares Outstanding","TTM",$B$1,"","USD","",$B$1) -> 814650000 | E8: =_xll.PBF(A8,"Net Debt","TTM",$B$1,"","USD","",$B$1) -> 7140000000 | F8: =_xll.PBF(A8,"EBITDA","TTM",$B$1,"","USD","",$B$1) -> 4746000000 | G8: =_xll.PBF(A8,"EBITDA","NTM",$B$1,"","USD","",$B$1) -> 4746000000 | H8: =_xll.PBF(A8,"Diluted EPS (Analyst Normalized)","NTM",$B$1,"","USD","",$B$1) -> 3.57 | I8: =G18*D8 -> 62768782500 | J8: =I8+E8 -> 69908782500 | K8: =IFERROR(J8/F8,"") -> 14.730043 | L8: =IFERROR(J8/G8,"") -> 14.730043 | M8: =I8/(D8*H8) -> 21.582633
A9: NYS:CHD | B9: Church & Dwight | C9: =_xll.PBF(A9,"Total Revenue","TTM",$B$1,"","USD","",$B$1) -> 6141000000 | D9: =_xll.PBF(A9,"Diluted Weighted Average Shares Outstanding","TTM",$B$1,"","USD","",$B$1) -> 246300000 | E9: =_xll.PBF(A9,"Net Debt","TTM",$B$1,"","USD","",$B$1) -> 1899200000 | F9: =_xll.PBF(A9,"EBITDA","TTM",$B$1,"","USD","",$B$1) -> 1329200000 | G9: =_xll.PBF(A9,"EBITDA","NTM",$B$1,"","USD","",$B$1) -> 1329200000 | H9: =_xll.PBF(A9,"Diluted EPS (Analyst Normalized)","NTM",$B$1,"","USD","",$B$1) -> 3.18 | I9: =G19*D9 -> 21598047000 | J9: =I9+E9 -> 23497247000 | K9: =IFERROR(J9/F9,"") -> 17.677736 | L9: =IFERROR(J9/G9,"") -> 17.677736 | M9: =I9/(D9*H9) -> 27.575472
A10: NYS:ABT | B10: Abbott Laboratories | C10: =_xll.PBF(A10,"Total Revenue","TTM",$B$1,"","USD","",$B$1) -> 43843000000 | D10: =_xll.PBF(A10,"Diluted Weighted Average Shares Outstanding","TTM",$B$1,"","USD","",$B$1) -> 1747795250 | E10: =_xll.PBF(A10,"Net Debt","TTM",$B$1,"","USD","",$B$1) -> 5208000000 | F10: =_xll.PBF(A10,"EBITDA","TTM",$B$1,"","USD","",$B$1) -> 11457000000 | G10: =_xll.PBF(A10,"EBITDA","NTM",$B$1,"","USD","",$B$1) -> 11457000000 | H10: =_xll.PBF(A10,"Diluted EPS (Analyst Normalized)","NTM",$B$1,"","USD","",$B$1) -> 7.98 | I10: =_xll.PBF(A10,"Market Cap","TTM",$B$1,"","USD","",$B$1) -> 214959350088 | J10: =I10+E10 -> 220167350088 | K10: =IFERROR(J10/F10,"") -> 19.216841 | L10: =IFERROR(J10/G10,"") -> 19.216841 | M10: =I10/(D10*H10) -> 15.412138
A11: NYS:COTY | B11: Coty | C11: =_xll.PBF(A11,"Total Revenue","TTM",$B$1,"","USD","",$B$1) -> 5892900000 | D11: =_xll.PBF(A11,"Diluted Weighted Average Shares Outstanding","TTM",$B$1,"","USD","",$B$1) -> 870900000 | E11: =_xll.PBF(A11,"Net Debt","TTM",$B$1,"","USD","",$B$1) -> 3988100000 | F11: =_xll.PBF(A11,"EBITDA","TTM",$B$1,"","USD","",$B$1) -> 285600000 | G11: =_xll.PBF(A11,"EBITDA","NTM",$B$1,"","USD","",$B$1) -> 285600000 | H11: =_xll.PBF(A11,"Diluted EPS (Analyst Normalized)","NTM",$B$1,"","USD","",$B$1) -> -0.44 | I11: =_xll.PBF(A11,"Market Cap","TTM",$B$1,"","USD","",$B$1) -> 3469214184 | J11: =I11+E11 -> 7457314184 | K11: =IFERROR(J11/F11,"") -> 26.111044 | L11: =IFERROR(J11/G11,"") -> 26.111044 | M11: =I11/(D11*H11) -> -9.0533674
A12: NYS:EPC | B12: Edgewell Personal Care | C12: =_xll.PBF(A12,"Total Revenue","TTM",$B$1,"","USD","",$B$1) -> 2203900000 | D12: =_xll.PBF(A12,"Diluted Weighted Average Shares Outstanding","TTM",$B$1,"","USD","",$B$1) -> 48375000 | E12: =_xll.PBF(A12,"Net Debt","TTM",$B$1,"","USD","",$B$1) -> 1212600000 | F12: =_xll.PBF(A12,"EBITDA","TTM",$B$1,"","USD","",$B$1) -> 245100000 | G12: =_xll.PBF(A12,"EBITDA","NTM",$B$1,"","USD","",$B$1) -> 245100000 | H12: =_xll.PBF(A12,"Diluted EPS (Analyst Normalized)","NTM",$B$1,"","USD","",$B$1) -> 1.35 | I12: =_xll.PBF(A12,"Market Cap","TTM",$B$1,"","USD","",$B$1) -> 900941691 | J12: =I12+E12 -> 2113541691 | K12: =IFERROR(J12/F12,"") -> 8.6231811 | L12: =IFERROR(J12/G12,"") -> 8.6231811 | M12: =I12/(D12*H12) -> 13.795643
G15: {=_xlfn.STOCKHISTORY("KVUE",$B$1,$B$1,0,0,1)} -> 14.37
G16: {=_xlfn.STOCKHISTORY("PG",$B$1,$B$1,0,0,1)} -> 150.37
G17: {=_xlfn.STOCKHISTORY("KMB",$B$1,$B$1,0,0,1)} -> 119.71
G18: {=_xlfn.STOCKHISTORY("CL",$B$1,$B$1,0,0,1)} -> 77.05
G19: {=_xlfn.STOCKHISTORY("CHD",$B$1,$B$1,0,0,1)} -> 87.69

Sheet PB_CACHE
A1: H4sIAAAAAAAEAO2dCXxN1/bHc865pqBqKFpKzEFEIklRU2QQQyQhQY2RxCXhStKbRBtapa2WTlqqSgdaFK+oGh4dKIoaq2ipoW0MrbHqGfq8Ev3vfXPX9dsnd597cuN9Pv/P+4hPyZH4/tbee+2191l77dRH8fHx+Zt98D/5RyWV/dYnISM3LT0iK2uMX1J+tjXHLzYj1Z5izw/w62+152RkZXZqE9TmkcBg9isowC8yz5abZ7d2yrTm5dpTbAF+CXmptoy0Xtb8pKwx1sxOmXk2WxnOT3Rhkx3YZCc2MNFqz0ixZYxPSbVZI1PS0q3F/6ZlUlZ2rHWc1eZ4ispIy2VmsH9rYdxyTqvKR2aNzU6xW+3lu6fkpCdmjLdWZkb0T7HlWRNSMuw5PpqPVn6Gkpifk2sdGxiZZbNZHZicwBhrJhNMoz+jH89j4rn5xBsePHiw818l5tozMkcF+I3NScuy2zJS73RJaGAQ/+W5P1Lbtk0JSwt7JLh9SKg1qF37oUPL/0M1MArbMLzNf9WSgMGlGSLd0DC5u+1GQ4cOHsodVGP/VdDoE+4DFv7Z/8ex5ZOqHLfQR3Haqy25N9omR9tyk4Wme91ltrscU2OMNb/MON4liqXXXTSYs8uWZb/d1yMhPpnZFpIcFJYcFFqhHHftG2yc+FiVrcCeqiZk5eQGD+TfFOr8Jl/+Tdfpmyqxp2oJdmuUNcXGvyssOTgoOSS4QmX292U4724a/r+xQnz0vzMJRrClPCPtv7g6DKLVYRv/pAp3Pe5/3LH60JcG8k+q8i9Vdn4pQfhSdf63VShsc6K28N4QmAnZF9kMv9dV3oTrmLtkrCNUP8B+6xA3MPHR6ITIqAxbXq51hF9iOotVOX7xebk5uSmZI1h3JyX1DgprHRTamgf0folR/I9WQWGtgkIr1WKArt2y7GNTcnNKsfE/z9zhbjWMz86aHR3O03lMcnJEStoY1oZuGVbbiLodo6w5afaMbO5r+i/W6ljUDv3fq4qlurOFgQ5q0QNvuaMPa/PlrlG3HtGxUXHxSd3i+8VF+ZY5wxrk7l/xOFHOMZLJyT7lazk3e8pv7Nv5lChbhz015wPSNSIpzprrF2VNzZV3v3Ka/Rved+X5muu3zH6zq69yij1z+TIcfJLA9dlTWw7u1b9fdO8U+xgGj0zJzsh19CPvDwOZAqdMBd5WX+Vnp4LD9J9IoTF7io3ryhR6R5AvDbBmjErnn3QdZ7WnjLKWyLmUY9g6n5kt17DWHcXWHSFtf/bU0tltdxpngD58Bz3plSsxj3eL8FUOIfoHQgewp2bOKRId0SMpqmucHHsQLS6YEvMps/gAYvcTNogsjuweZcrifYD2X2JrW5NZ/C2i9xI6lNAJMY7u9ktgAdVqgN4tDu9OpO4gantHPxQNr8d+2I79MP/sknOsH7YhdithOzkikOg1JXKSLaLxm9A3vyKVCJpWrLdNTKsNaH74J88WMPO/RPO/IHA39tTaAY5PGpiUxWaTX1/rOGtmnlF/f4b4RyvPv8rw6xG/jvA92VNHp/P1ZvtlBk+zZuYWjahfttVe1FcGWmudWmVj3YQpZTWqriLVeG5WkQN5NSQrxSFZgUOynESS2FNj8qeERANn+ljELUXcEsINpJ7i8c0rqz8SZRaizAKSGeaw2hkNDK3+QMTNQ9z7hEtjT/5ktcdZ9S76zQ7Vfpb5zTs4gnOJO4r7rTiCzFo//66ZKTa2kfKL44sRC/zWEc0N9N526f3pP2T6lus1w32V2aj3FumN4dsAZ/wtheCbLsG+6+tNudDHlwnORMEZJJhFgmxCl0LwdZegQ2/9X118leko+BoJ5jgExTjlheArLkHeof5DarEWvoyCL5HgE64FItZcFJ8qOtwLSJ1C1KfIf1m/GfvvcyJuMvrvJMJNZk+tyH/NmTlR5D6FZk4g7gvsqQmFVWM780XeE2jnOOK9THZGxpoN0rk42VbVq1GVrbc5aKyd4NNpDeCdYBafjfiAdT9WZPgsxGcSfiZ7alpku8cIYUNq+s2RZ1iEGIPU0USdTREiMrYU7pyumz+32fwZhXojSe8dx+5QjBCl2x2OgLZOCh8ccpS1NQ21U0l7Hk0lvoqa2WsNx27ssugVvv4nI3oYoRewp97kqHenXUNQ3GfM6Z1MfDCKDyLxxTRLHKuH4Sx5TJwl/XGW9CPeMvbUomjVMNVNiTgCWzb368d8uC9a2ofIK7mTO8OOuTARLxrcG7GxhF1L0zohxuy864m9+2HVo22YzT0Q3p3gn7lsZkNrqj+6AfvJYZlTVcaORnYUsTc4ditFq4l3+7oI6p9YR/+Eo0wXktnCngKdk85sB3XCQa2xI7ERa0RHpHcg+nbavCTEmNhTt8eOH3zFpw7jtkNuW+LuojmFW7nSzakwFN96rMlxNqdCUTyExL+l1z2+QDrCrQE2GLHf3WjGp2oQYlsT9gA5EwtB5iZAK3ECtERsC8IeZk+9xH1e6TrKH1sUmj77JGtRM5RuStLHfJypo8hY7zy4sejBDVGlAakU0OKXEONxNOqj7VnjJ1RnHlYPqQ8T9TQtRrB7LF2/1UHt+zsPXc767SHUfpC0z9LOFVJuXqy8tVyCNVbEnBhfg6+8NVHwARK8SFGdTycTE7U6NiUo7b3vNvsq1ZBclciXaTPJwovx8lNFdObKuPxUItx1MpR5lJlw6wuGzr06Kaw1G+8KaGh5Iv+nWO7CAFsW2+/MXZRBrIWwhXrnNOgB1Y1zKkj1IaqiOMOqY+/rydrbtzHjFH/fHmZt4W3g3rrt5PLqio6UI/Nqxv51W5ixN1Dm3yTjy2Q6uZZNr3SuizpXUecK6VRRKP7cmcMlmrKXbws+eek2+OTvpFKDWuNIm3rVmgtia85ha86SzoOKbpNvAPztdvFN/q9IPU3UhxXnYsYnqCcPPYnYy7MWa8xDTyC2gLANFGf4hBBWuvD5M2qHDw2axpr0E2ofJ+0minNLw4bd7JbmKNJHlJtyjdGPIP1Hojdn9EbOYTAMaIdE5/kenecg0QIVeutkU8Hcqr9f5O5DK78lbohCgZJxTUT0Pdj+429uusTavxvJu4jcVnFuU5jDmDN4h2jwdsRuI2xHhg2mWWR+5nwtzpzNyN5E7K6KfsNmMGwbbxffsG1A7JeEjaZoyfPzXs37z0Xr16PMOpLpyWQi9O+PXmwH1roadrEPfxXfzLYDa1BxNSnGFV9eDLifulleViL3E+L2pZbgrt2Llix3KX59nWcdf2ctWYaKH5Nif0coKFrVzYaCpdie3X+cqMaC3BKkLyb6IFpfIGFRopi2SJwZCzBEfEgqyYpzA38nDVO6SDofG7jQ78IONmDzsIHvk3SaY64XdZ+5uf6u2KK5iJ1D2HSXf8WaCE2z0dz5L10tZOa+hdxZxLVRaBIPMA3YM4H9+gbb0mZsrGcg+w1iZyv6Mz4D7HRhShSd8b2G2FcJm0urCdsfGq4mL4sdOw1dZSrR8hXnqcwdVymRZ7wgijyPIs+RyESl2IGEAXIydoXzQGISdsUzxH3WFU4hzpXI/KdF8yeg+eNJ5kXFec7HBtKE9z2J9rf78L3vmf1PoP3jCPyyA1w0WUyAcxF8LXUhd+scBNsJPF3huUlnJsiMV2cDevQly8qmPHGM6ExCz6StEusMs/HRhobbwtvzzOcYpI8m+myKjwkx3q2P6eL6OBJVrKTybrEdrAExzc0ONhWw5Xgpl6NUi1d43SvVMlV/pKTQWMxXjN6iQ4vGItQ5Fsk4Fgn5G08xRxqGQzyUsAsV7xIiOsHBLsEJjoyIT7ivMggFB5LgEsW7ozyd4ADdRuUBJtgfBfuR4DLFzAGRDp+IHXg2emslnlxHfB/Cr1SkZ3o6ZrwYQ3tjDI0l3FrpqqWj9RRp3ZEWQ7TPFc8nbzputPB+29nK92hR2PJIgm80XLd12K7CVmN/1CrmkeGI7ULYLcZbZB23E3J9IsoeYNyOyO1A3O1mNqw6enukP3b+SBWeNkd6W6LvMkoh6KhhSK17qN2/eD4cqSFE/dYwAOuwwYhVL67mByBBiG1N2ANK6XP8OvFWwvgGvXGMtSkAxVuS+CFFfm6mgzYXfbwZ+nhT4h3z/NaswzYWsQ3RzAaELTCRPtBx64vch5Fbl7i/KobnNjrkQ9itfQPH1mJj+iByaxP3nDR5okPWFK2sgZ1anWiXFBNnVzpwVbT1WIdvGjJb70dbqxD9imJcEKYDVxY2it2Wcd+qhOCKBP7TU25GR66AZEvWU+cZuTySyxH5L8XD6ayOXOYOeVLMtKOz+7POsCBZI/JtMzk1HV0RIkjzhn8yu32Q/nehk66q0kIvHbOwUPCLm4XgF38RrpxqcCKkA94oBCOfCj9Vg3XBvwvByD+JWlE1yiLpsNcQO2lo5kHW9quIvULYKqpB7YaOermweEz+A6mXiFpdNawa03EvIvftQ0d+Y9wLyD1P3FpqCev+dEpnxfH7DcfvVxKpq3qqa9JRT4nUE2h6AVEbqB4OuXTQn7FT1nzY+S+ecEbycSI3UT2XOOngR0WLf0TuYeK2UD3mM3TYH8Dm3L7d6zVg3vw9sg8SO1D19FKpQ+8H9MnbE/s3YejvEL2P0G1UL9N8OsW9LsW9e/jHxS6+yh5U3E2Kj6gmXmN19J04vOUHXeSvsTuQ/g3RH1VLX8CjE9+G4tknRu5i4ltR/GsS76waZxV04M0I/j72Oe60mxD8FYEj1JIejumkNogu/AVO5c9JJUb1qspUJ7Xe1aqiF7fa7D1qHbbqn6TXS/VU5a9Dr4EOy6kz0h7N3Ho1olcROl4t6UUYndRKscNWYIctJ5Uk1Uy1uI78MY56zTppfKX9BzZiKeEfU42uKuiwixHrfB36CLGLCDtELfXFDp32AtSeOjWIX+z4ELU/IO3hqqdrEjr0PECvGVyzRW025O8j+j1Cj1BLfYqp035H2Bc8P3Uqa9Zc1J5D2umqx9y7jj1b9K9ZiH2TsGNVaXW6DjdDxL2O7jqdcHa1xElbncyroszLKPMSyTyhlro0VCc7FQZiUtPLlXlp6IvYYy+Q9gS1pKc8OqnnxRY+iy2cTCqT1FLXG+lkn0FX+27fRF5vNBFb+DRpP68alpPouBOQ60xmjEduPnGnqobnPDruE8j1HzfwFuOOQ24ecV9R5aXfOmiO2PePY99nE+8N1UNVkQ6aCZYuu1p2YzALIGPRUhuRZ6nS8icdc7RoaDoaOopwc9USnu/oRKyiSBqKpJLIPLW0BYM61eE4sHMHjuUFg8nYXcNIeoFqVIyiww5BrDOTNBixgwi7WPXuJohO8DGXYIjjowLbhQxAwf4k+LHqqZpch06CtoTn/asRLz5NRHRfQn+ieneNRieY4BJ0lAau4G2JR8E4Elytf5k2oMa6eZnuhdSeRF2nelnUoFPs7lIc6fg4xN4RYlCxGyl+oZb2GF0nHYWNzd20hB+jR6J0BEl/xaQfktS2MKYS7iSV3cy+sWKjAX3j42J6xCX0S/JVOiOwEwG3qp6ub+ps7SBO/PZIbUfUnarnUnkd9xHsg31DZ4SwAQ9DeCjB96oey/t17DaizUGIbU3YA6rxZWh9AhjtPT5qOj90DUBwSwIfUo3usupTwIh1nmT5I7YZYY+qJb3LqpNqIvZKIwzhDUnlF9XjvQQd1g9asL5+3gB+LlofW1CP2KeKpcEMsHWF7W5RGqwOYh8i7JniCSsDbm3kOhNWtZBbk7gX1BJf+tRp1RB7vBr2eFWSuax6dVdKJ1XF1azuPCjH8Kh8HzarMuldUz1eFtCxK4rNqIDY8oT9j2pcHKFjlsVh+LHnPr4VLAPgcvynnzhO0/kPRbl3mm7uNN1Co1EojZnBQa1DgvmAhBUNSFir4KBWIcGKKg6yDw7y37co266ZTGTIVApviUn4W5iEJ5VymvxwRga+cQteylpNHN2YJ+NvYTKe6BU16Volg18DePgXI7fzteoqwq8QvIrm9uRHBr58C4PcL7F88/YHgi8RuLrmdrWSgS8iePiXI/kPAbiA4PMErqW5P1KSkc8iOXfVP39n5DNI/o3IdTR3J4Ey7mnk/r2/Gj8JPIXck8Str5lcCGVSBaIT/oxO+BOpNNa8fJeRqR7DBlbK78DfZY5iA4+QtL9W/BBKRj2M1FlVP+U/uOMQUn8gaoAmebOQoQ/ilNqw4AjPNB9A9H5CB2ny0gMZfR8aXu/W8vv4TxxB+l6ih2ruCiZk3N3I9TlXhhdQ7kLuTuK200r2IiFT/Mal2Nxx7f74V77KdlTcRoodtWLZBxn0a9FHN6OPbiJeV8199kEG3Qh9s2vi1gsBrM83oKVfEjla02cfZMzPRUPXo6HrCNdTkx1HybBrwdQb8wpWPMhMXYOmriZ2nOYuVSTjforucX/HOfyUYyVyPyFuX81N+Y8Muxyxm4615RmzZYj9mLD9NYNyLRl+KeLn7grh5VpLEL+Y8IM0r0+cZOKLUPz17Gv8WsNCFF9A4sM0tydOMvAHCB7S7twNBp6P4HkETtXcZHdk2PcQO6P+gDKss95F7DuEHamVZOst05vj0nP80I3pldjW+23Um016o7USZZNkgrNcgo938j28IJvv9d9EwZkkmKkVq0WSQd8Q5/F0nMevES9Hk2QPZNRXROpLaOU0oj6p6Up7ZLQXRdoUtPF5oj2tSc7xZNRnwV8WruxRtgfzl8lo6CRCTy4WEgyMnegmJDyN2KcIO0WTV8jI6OOR/uZzBfzcLh/pTxJ9miZ7o5exxyG7k88Rfkc1D9m5xH5VkxygydB2QL+9KOVdflH1cURnE/qNYlPeAJvpZsqPRayNsLOKbyYMuKPdbCYykJtO3Dmam9yGDDsSsQUTv+W5DStiRxD2Pc3bsx2ZdqrgluOHcLdMQe3hpP2B5q4QSMYdhtzLf1TgeZWhyB1C3EVa8VJSGXUQUtMbreBlSwOR+hhRl2olKReQ6fV36RUlheuw0NoP9ZJIb7lmsghCJtVXDGYJGMziSWWVJq0PknF7i9xeaH1P4q7TdGXYMlp3kdYNrYwm2pea+/ooGTQSR9X/mbf4eV0E2tmVyJs0L1PvMukuKN29RwxPvXdG6U4kvVWTlDnJ0B0Afe3onmd4feijiG5P6B2aucM4mVJbcVDCcFBCSWRv8elrgGzjZvoGo/FBxN2vlaxGS6YY6FIsOkc608VXaYWKAaT4gybLWMrYLcQO8kdsM8Ie1czmd2UyTUSZRjgODUnmF83bAheZrB+O1XpbwWo2VvWxifVI+5QmLfKWweuKbXoIuQ8S96xmUGokI9dCs3uevXqdmV0T8Q8Q/qLmbfGMTLu6sOo1rfoi066G2lVJ+7Lm5vRGhq0iYGvM5rPmPsRWJuw1zX19tYxc8Q55k2X/qZwkFkx8kVyByDc02f0AGbucOMRlEGshbKGmr/aRZo5FnA/OAv7D9osyxxZz1b/SxPFNMXF8ExPHJML/Jxf6gmhpwvhm8Z3Fv29iwpioFS0lOjeXJpFdgkWX6OuzrcVVFLxCglUsJsuGpGllsbMuYWf9Tio1LG4u3MmIF24Wd/TzaPw5wta2SCqwZegzorG/IvU0UR+2SC96ybgn0eRpz6zjF71OILyA4A0sJbqyJxP82SW4MJu/l/OfvvkTCh4nwSYW/Z06GfOo2Dk/4kgeJlwLS4nuOMq0fnDZP3cO/7jOFuTv0f6DJBho8fp+lUx8P47WEm0tPwn5DsX3kXgbS/GqEhl1L1Kd2fE9SN1N1Ecs3pYJyrR3gvak2PiKvExwB2p/Q9qPWmT1mjL2NtEtvkbsFsJ2sZgtsJTJbBJlNqL3bSCZKIubyy0y4hc4IM4338/R+s8I292iv9gjY64TrVyLVq4hXG+LvM5fBl6FxlZ6Zwyv8/8UjV1J9D4Wt4ffMvAKBK9cXZUffi8HcMX/A5x5ryIUbQAA

Sheet Summary
A1: Company | B1: IPO EV/NTM | C1: 1Y EV/NTM | D1: Pre-Deal EV/NTM | E1: IPO P/E | F1: 1Y P/E | G1: Pre-Deal P/E
A2: Kenvue | B2: =IPO_2023_05_04!L5 -> 15.147322 | C2: =Post1Y_2024_05_04!L5 -> 13.878383 | D2: =PreDeal_2025_10_31!L5 -> 11.953281 | E2: =IPO_2023_05_04!M5 -> 28.924731 | F2: =Post1Y_2024_05_04!M5 -> 21.333333 | G2: =PreDeal_2025_10_31!M5 -> 19.418919
A3: Procter & Gamble | B3: =IPO_2023_05_04!L6 -> 19.935901 | C3: =Post1Y_2024_05_04!L6 -> 19.257388 | D3: =PreDeal_2025_10_31!L6 -> 16.119246 | E3: =IPO_2023_05_04!M6 -> 27.092334 | F3: =Post1Y_2024_05_04!M6 -> 26.872549 | G3: =PreDeal_2025_10_31!M6 -> 21.951825
A4: Kimberly-Clark | B4: =IPO_2023_05_04!L7 -> 16.49981 | C4: =Post1Y_2024_05_04!L7 -> 20.080787 | D4: =PreDeal_2025_10_31!L7 -> 15.371798 | E4: =IPO_2023_05_04!M7 -> 24.72774 | F4: =Post1Y_2024_05_04!M7 -> 25.016544 | G4: =PreDeal_2025_10_31!M7 -> 20.255499
A5: Colgate-Palmolive | B5: =IPO_2023_05_04!L8 -> 24.065756 | C5: =Post1Y_2024_05_04!L8 -> 18.269789 | D5: =PreDeal_2025_10_31!L8 -> 14.730043 | E5: =IPO_2023_05_04!M8 -> 42.078125 | F5: =Post1Y_2024_05_04!M8 -> 29.392405 | G5: =PreDeal_2025_10_31!M8 -> 21.582633
A6: Church & Dwight | B6: =IPO_2023_05_04!L9 -> 31.124392 | C6: =Post1Y_2024_05_04!L9 -> 21.557797 | D6: =PreDeal_2025_10_31!L9 -> 17.677736 | E6: =IPO_2023_05_04!M9 -> 58.479042 | F6: =Post1Y_2024_05_04!M9 -> 33.685714 | G6: =PreDeal_2025_10_31!M9 -> 27.575472
A7: Abbott Laboratories | B7: =IPO_2023_05_04!L10 -> 18.967745 | C7: =Post1Y_2024_05_04!L10 -> 19.137757 | D7: =PreDeal_2025_10_31!L10 -> 19.216841 | E7: =IPO_2023_05_04!M10 -> 33.325292 | F7: =Post1Y_2024_05_04!M10 -> 32.823662 | G7: =PreDeal_2025_10_31!M10 -> 15.412138
A8: Coty | B8: =IPO_2023_05_04!L11 -> 14.953573 | C8: =Post1Y_2024_05_04!L11 -> 11.523528 | D8: =PreDeal_2025_10_31!L11 -> 26.111044 | E8: =IPO_2023_05_04!M11 -> 81.802431 | F8: =Post1Y_2024_05_04!M11 -> 33.48962 | G8: =PreDeal_2025_10_31!M11 -> -9.0533674
A9: Edgewell Personal Care | B9: =IPO_2023_05_04!L12 -> 12.434365 | C9: =Post1Y_2024_05_04!L12 -> 10.279838 | D9: =PreDeal_2025_10_31!L12 -> 8.6231811 | E9: =IPO_2023_05_04!M12 -> 22.366328 | F9: =Post1Y_2024_05_04!M12 -> 17.817945 | G9: =PreDeal_2025_10_31!M12 -> 13.795643
A12: Metric | B12: IPO (All Comps) | C12: 1Y (All Comps) | D12: Pre-Deal (All Comps) | E12: IPO (Core Excl.) | F12: 1Y (Core Excl.) | G12: Pre-Deal (Core Excl.)
A13: Peer Median EV/NTM | B13: =AVERAGE(B3:B9) -> 19.711649 | C13: =AVERAGE(C3:C9) -> 17.158126 | D13: =AVERAGE(D3:D9) -> 16.835698 | E13: =AVERAGE(E3:E6) -> 38.09431 | F13: =AVERAGE(F3:F6) -> 28.741803 | G13: =AVERAGE(G3:G6) -> 22.841357
A14: KVUE EV/NTM | B14: =B2 -> 15.147322 | C14: =C2 -> 13.878383 | D14: =D2 -> 11.953281 | E14: =B2 -> 15.147322 | F14: =C2 -> 13.878383 | G14: =D2 -> 11.953281
A15: KVUE Discount to Median | B15: =IFERROR(B2/B13-1,"") -> -0.23155481 | C15: =IFERROR(C2/C13-1,"") -> -0.19114811 | D15: =IFERROR(D2/D13-1,"") -> -0.29000386 | E15: =IFERROR(B2/E13-1,"") -> -0.60237313 | F15: =IFERROR(C2/F13-1,"") -> -0.51713597 | G15: =IFERROR(D2/G13-1,"") -> -0.47668254
A17: Peer Median P/NTM | B17: =AVERAGE(E3:E9) -> 41.410185 | C17: =AVERAGE(F3:F9) -> 28.442634 | D17: =AVERAGE(G3:G9) -> 15.931406 | E17: =AVERAGE(E3:E6) -> 38.09431 | F17: =AVERAGE(F3:F6) -> 28.741803 | G17: =AVERAGE(G3:G6) -> 22.841357
A18: KVUE P/NTM | B18: =E2 -> 28.924731 | C18: =F2 -> 21.333333 | D18: =G2 -> 19.418919 | E18: =E2 -> 28.924731 | F18: =F2 -> 21.333333 | G18: =G2 -> 19.418919
A19: KVUE Discount to Median | B19: =IFERROR(E2/B17-1,"") -> -0.30150683 | C19: =IFERROR(F2/C17-1,"") -> -0.24995226 | D19: =IFERROR(G2/D17-1,"") -> 0.21890804 | E19: =IFERROR(E2/E17-1,"") -> -0.24070731 | F19: =IFERROR(F2/F17-1,"") -> -0.2577594 | G19: =IFERROR(G2/G17-1,"") -> -0.14983515

Sheet Sheet1
