Workbook

Sheet PB_CACHE
A1: H4sIAAAAAAAEAO3aDWxUVRYA4D5a2lL+KpBCoAsTMdK1pX3zP+W/P9BiSzvrVBALDNPpgw4dOjgzBQtEiLhgxAABFwgQcYVAFwgQMWLECAEDLhAgwgIrrhDYFVZ2lxVWILKZ7r3Tdzpn+u673q6YGFNJKNNOv3PnnHvPve89E6SEhIQW8h/9Sv/r0YX89RunL+ytKwwE6g1VTfOUkKHcVxP0BJtyDJOVYMgXaBhtkk22XCP5I+cYihr94cagMrpBaQwHPf4cg7Oxxu/zlilNVYF6pWF0Q6Pf35X6rjbWHWXdKpvrUoI+j9+30FPjV4o83jpF+53sqsC8cmW+4o++KvZ5w2QY5HeTiJuijiq1KDB3nieoBFNLPaE6l2+h0pMMYrLH36g4Pb5gKCExITF1reRqCoWVublFAb9fiTKh3BKlgQT0wtfxLzWS4OEm8GYaq6vV33KFg76G2TmGuSFvIOj31cRSYsmV6Z8fzkeN3e6xeq02Y77ZosiO/OnTU3d14QwKf4aZpp90JDnVP6ZE7UpDwj3uaTR9evV0OkFp1bsl0tLTf9BXSfTVz7G2dFGl0BEmSOrAE5s7qy1Y7aRHpDV1pks0XXRpJNYrTV3n05RISWWPccDUTk6mf7nqFCVs7EaXnvSQ1IfWKLkbedVrorPSTUZtdstWt2zplkbf8R28owd59YQzEAobp9I3WdQ39aRvugtv6k1e9XEGlWLF46fvsrqNstts7JZOvt+VRnycH+mXsXfs+OUsj1qyyfu8P+G+MRH2jan0H33o1EtTd5F0+NET9B/96I96Mn+UQX+UzvzRAPrdPtDrabDE7Z3VEenzN8ni70zV/9PjSx7TYKP9fSD5K6ts8vPjC2rnNJIE1xrGF06sKi6oqppkNObJxjzauJ93FVus1nx7j0zy7oIJgeBcTzj0Iy4N/kZq/7g+BV2KGaOiM2VMvdtd6PHWk/kxwaf4azNHFSshb9A3j06s9j/sP6r1c7T/fhcpqa/6CXOjausL+slpwlLphnhkge3vBWldb5CPwXovbQUp0WK53Qmp9De70gZxnbydzvrkITo5r6iaJJvjcm62mqRr5FdowqKRDbmZtwrSpKvkNY0edb8Cd6h+LeX8+FqabdKX2G39RNIV7H4B7jCB8Vqjrt1oly5jd82WY9S9hN2L4GaTV8N1xmvNky3UNROXfhkuW4fLFukCxuWv//INwc9j/HPA83TwCn38HAM/i/EzgJs5mTapGbHRjNhkq0U6HefuD9CMnMLuSXDtHNcS5xqNZukz7Dav2kzdE9g9Du5IjuuIq6DDLkufYvdhWgZ1j2H3KLhjOd1DVl1z1DXJsnQEuzOb6uhMPozdT8AtEhivOpNlq/QxduuyNlL3EHY/ArdEfya3jbc1D/lmo/Qhdgfs+RXNw0HsfgBumcDKa82DkeT3fUYeDmD3PXArOW58dzblm6T92C31//kmcfdhdy+4Ls6KNsXlwebIl/bEjXffRZqH3djdBe4UznwwxY3XZrJLzQx3J3Z3gFstsN5i493OcLdh911w3Zw8aOv2DqNuW7H7NrhegfyqHd5klrYw6rYZu5vAnc1xtetiI2NdbMDuenDrOfm1x7kWu0V6i+Guw+5acAMC81ftkyQPaxh9cjV2V4EbEji1qH2HrOM3GXVbid03wF3Aya81Pg+k/77eot2ZV2B3ObiLOHmwxfdfOV96jdF/l2H3VXCXcMZrix+vxSItZdRtCXZfAXeZwHhj7mKGuwi7C8FdIVA3tf/aTNLLjP67ALvzwV0psC7UdWzOl8LYbf7tDOqGsBsEd7VAP1PHS/rvPMb8DWC3Adx1AicqdV04TJK/RbvP12N3DrgbBNaxmgfZIdUx8jAbu7PA3cxxtSfA2hbtCdCL3Rpwtwr0B7WvWx3STEZfd2N3BrjbBM4PsfkwjZGHauy+CO5OgTzE6vYCo25TsDsZ3N2c+aDd56sY+4ULu8+Bu4/j2uP7DsmDk9F3KrFbAe4BjmuJ398cZqmc0SfLsPssuAcFzr8xt5ThlmB3AriHBM5n6jqWjVIxo+8UYbcQ3MMC55LYPj+OUbex2B0D7jHyKp+6xT5/Y5R1ugxZBQ0ef1MobKigV5nkelip/TXemNQFaHdIo9oC3c+atvrod9fGpkkjcaAREOgE50CsPbA5GAvQjl0buKcEJnRsYVsYrhm7JnDPCjRkdeO3GSWZkfA87OaCe15gocQaZw6jYWRj9xlwLwlcIMUuOLIYE28Ydp8G9wpn4mnnw1OMhjwUu0+Ce1VgvOoB02aTDNhVbyEMwe5gcG8IHIhjF8yZLdqNdBB2B4J7U+CCLjbeAYzx9sduBri3BdZFbOPvxxhvX+z2AfeOwIGtdZ7JpG7pcW7rDYne2O0F7j2BhqzOB4tD6sGYD92xmwbuA4H8xi7wU+PWcetBOwW7yeA+Epi/sYN2EqPRJ2K3C7gtnPFqbmdKCYz50BJBbiSiuonSD18oxm6t/TeidR9h93twU/RdxoXMw4g2vw+wex/c7hxX2yf/E9H2yXvYvQtub04etBd0/45o18Ud7P4L3L46Lj5YxW6J/iOinQ+3sfsNuP0F8hu74LgV0fbfm9j9GtxBnDxo++9fI9r1dgO718EdwsmDdh1fY7hXsfsVuEM549XeAPwyoj0IXsHuF+AO47jaGweXsateKF7C7kVwszmu9oL5AmO857H7Obh5HFd7g/UcdtUD/FnsngHXLNAfYgfM04x5dgq7J8G1c+aDdr/4LKLdL05g9zi4Izmu9sLgU0Z+jyE3hT48jT4BpU9HO5+ACj3Wk45CMcaSzMkVU10jxjuLxB+FHMFFWTpr9wF6Nx0X+xPwi4ifR31nifjDkI8xP7Df930L06RDmP8I+JLo8AtcI8omFYr7H2J/3MiE2/TmOvY/AL+M+EY6/KLKqqniAd6P24T3Jp+md9lxgPcgQCXkv6i0WNzfj/3LyvLz9G479veC7+J8AE6B9zA+wG4cYBcEmKJfAY7fzKjATuzvAL8aJlBRuXh+tsfxv6v5J70Lj/l3gXdD/gsKq8T9d7A/5/j1JDJBt2L/bfC9+uuL429hrK/N2N8E/mzd9cXJ/kbG+tqA+fXA1+tmn8O/xcj+OsyvBT6gP/s5/hrG7F+N/VXgh/Sry/HfZFR3JfbfAH8BrK6OPUl+nbFXrsABlkOARZwAnPnzGiPAMrxpZnRumh3fNF+Fqixpa6qlxQZO2S2tVbGoVVmKq+I4479An4GoVaH/K4n0CgRYRgKYoOwdiLCYcXGyCEdYCBFWQAS6L3Qgwss4wrWLvz9Ln4vgCPMhwkqxztfOD8d9guz7tPOF8NIIgr9abOtv58/D/q0Tc6PPSbDfAP46GL+zpAP58WN/76b1GaR31OP8zAF/g9DG1o6vw/ziU3/8lj42wcOfBfzmttZa3oHh1zJ8Lx5+DfhbBTtTuwAzGTPUjT/ADAiwTWxnbudPi6vvw28TSf6rsf8i+DuFTqbt+BcY5Z2C+cnA74b8kOF3oABVjPG7cAGegwD7IABZXx0I4GQssEocoAICHIgGaF1gHQhQzlhhZTjAsxDgoNjZt51fyuiiJbgEE8A/JHh4bxegmNHiivDmOaBz8+z45lkIVTnMvWAwynnmtjsA9MtwozzcbJTGMfrGWFz1MeAf4x1Z9fhRmE+XCu4SfiTmRwB/gj+p9AI44m7nVA8+Rx9f4QA2CHCKuyr0fAv2N/6h+U/0MRb2TeCf5Z6J9XwZ+4NPrk0mfSkP+7ngn+efifUC5DDuS2XjAM9AgEu8Sx49Pgvzs6sz+5PxD8P808Bf4W9segGeYox/KA7wJAS4yr8k1wtgYMygITjAYAhwg3tPR8/PjFthLw2kG8Mg7A8E/ybv5KLHD2CssP6YzwD+Nnfj1/P7MSZoX+z3Af8Ob+PX49MZ86c35nsBf4977tXzezCy3x37aeA/4F4z6/mpjP6Qgv1k8B9xz9V6fhKjPyciv/v/AKqQe4X8OwAA

Sheet Sheet1
A1: Snapshot Date | B1: 2023-05-04 | C1: KVUE
A2: Use same date for Date + Effective Date in all formulas
A4: Date | B4: Revenue TTM | C4: Net Debt | D4: EBITDA TTM | E4: EBITDA NTM | F4: Diluted EPS | G4: Shares Outstanding | H4: Date | I4: Share Price | J4: PE Multiple | K4: Enterprise Value | L4: EV/EBITDA
A5: 2023-05-04 | B5: =_xll.PBF($C$1,"Total Revenue","TTM",$A5,"","USD","",$A5) -> 14950000000 | C5: =_xll.PBF($C$1,"Net Debt","TTM",$A5,"","USD","",$A5) -> -1115000000 | D5: =_xll.PBF($C$1,"Adjusted EBITDA","TTM",$A5,"","USD","",$A5) -> 3606000000 | E5: =_xll.PBF($C$1,"Adjusted EBITDA","NTM",$A5,"","USD","",$A5) -> 3606000000 | F5: =_xll.PBF($C$1,"Diluted EPS (Analyst Normalized)","NTM",$A5,"","USD","",$A5) -> 0.93 | G5: =_xll.PBF($C$1,"Diluted Weighted Average Shares Outstanding","TTM",$A5,"","USD","",$A5) -> 1888972560 | H5: {=_xlfn.LET( _xlpm.data, _xlfn.STOCKHISTORY("KVUE",$A5-10,$A5,0,0,0,1), INDEX(_xlpm.data,ROWS(_xlpm.data),0) )} -> 45050 | I5: 26.9 | J5: =I5/F5 -> 28.924731 | K5: =(I5*G5)+C5 -> 49698361864 | L5: =K5/D5 -> 13.78213
A6: 45078 | B6: =_xll.PBF($C$1,"Total Revenue","TTM",$A6,"","USD","",$A6) -> 14950000000 | C6: =_xll.PBF($C$1,"Net Debt","TTM",$A6,"","USD","",$A6) -> -1115000000 | D6: =_xll.PBF($C$1,"Adjusted EBITDA","TTM",$A6,"","USD","",$A6) -> 3606000000 | E6: =_xll.PBF($C$1,"Adjusted EBITDA","NTM",$A6,"","USD","",$A6) -> 3606000000 | F6: =_xll.PBF($C$1,"Diluted EPS (Analyst Normalized)","NTM",$A6,"","USD","",$A6) -> 0.93 | G6: =_xll.PBF($C$1,"Diluted Weighted Average Shares Outstanding","TTM",$A6,"","USD","",$A6) -> 1888972560 | H6: {=_xlfn.LET( _xlpm.data, _xlfn.STOCKHISTORY("KVUE",$A6-10,$A6,0,0,0,1), INDEX(_xlpm.data,ROWS(_xlpm.data),0) )} -> 45078 | I6: 25.28 | J6: =I6/F6 -> 27.182796 | K6: =(I6*G6)+C6 -> 4.6638226e+10 | L6: =K6/D6 -> 12.933507
A7: 45108 | B7: =_xll.PBF($C$1,"Total Revenue","TTM",$A7,"","USD","",$A7) -> 15212000000 | C7: =_xll.PBF($C$1,"Net Debt","TTM",$A7,"","USD","",$A7) -> 6102000000 | D7: =_xll.PBF($C$1,"Adjusted EBITDA","TTM",$A7,"","USD","",$A7) -> 3405000000 | E7: =_xll.PBF($C$1,"Adjusted EBITDA","NTM",$A7,"","USD","",$A7) -> 3405000000 | F7: =_xll.PBF($C$1,"Diluted EPS (Analyst Normalized)","NTM",$A7,"","USD","",$A7) -> 1.01 | G7: =_xll.PBF($C$1,"Diluted Weighted Average Shares Outstanding","TTM",$A7,"","USD","",$A7) -> 1888972560 | H7: {=_xlfn.LET( _xlpm.data, _xlfn.STOCKHISTORY("KVUE",$A7-10,$A7,0,0,0,1), INDEX(_xlpm.data,ROWS(_xlpm.data),0) )} -> 45107 | I7: 26.42 | J7: =I7/F7 -> 26.158416 | K7: =(I7*G7)+C7 -> 5.6008655e+10 | L7: =K7/D7 -> 16.448944
A8: 45139 | B8: =_xll.PBF($C$1,"Total Revenue","TTM",$A8,"","USD","",$A8) -> 15212000000 | C8: =_xll.PBF($C$1,"Net Debt","TTM",$A8,"","USD","",$A8) -> 6102000000 | D8: =_xll.PBF($C$1,"Adjusted EBITDA","TTM",$A8,"","USD","",$A8) -> 3405000000 | E8: =_xll.PBF($C$1,"Adjusted EBITDA","NTM",$A8,"","USD","",$A8) -> 3405000000 | F8: =_xll.PBF($C$1,"Diluted EPS (Analyst Normalized)","NTM",$A8,"","USD","",$A8) -> 1.01 | G8: =_xll.PBF($C$1,"Diluted Weighted Average Shares Outstanding","TTM",$A8,"","USD","",$A8) -> 1888972560 | H8: {=_xlfn.LET( _xlpm.data, _xlfn.STOCKHISTORY("KVUE",$A8-10,$A8,0,0,0,1), INDEX(_xlpm.data,ROWS(_xlpm.data),0) )} -> 45139 | I8: 23.65 | J8: =I8/F8 -> 23.415842 | K8: =(I8*G8)+C8 -> 50776201044 | L8: =K8/D8 -> 14.912247
A9: 45170 | B9: =_xll.PBF($C$1,"Total Revenue","TTM",$A9,"","USD","",$A9) -> 15419000000 | C9: =_xll.PBF($C$1,"Net Debt","TTM",$A9,"","USD","",$A9) -> 7372000000 | D9: =_xll.PBF($C$1,"Adjusted EBITDA","TTM",$A9,"","USD","",$A9) -> 3276000000 | E9: =_xll.PBF($C$1,"Adjusted EBITDA","NTM",$A9,"","USD","",$A9) -> 3276000000 | F9: =_xll.PBF($C$1,"Diluted EPS (Analyst Normalized)","NTM",$A9,"","USD","",$A9) -> 1.05 | G9: =_xll.PBF($C$1,"Diluted Weighted Average Shares Outstanding","TTM",$A9,"","USD","",$A9) -> 1832986280 | H9: {=_xlfn.LET( _xlpm.data, _xlfn.STOCKHISTORY("KVUE",$A9-10,$A9,0,0,0,1), INDEX(_xlpm.data,ROWS(_xlpm.data),0) )} -> 45170 | I9: 22.96 | J9: =I9/F9 -> 21.866667 | K9: =(I9*G9)+C9 -> 4.9457365e+10 | L9: =K9/D9 -> 15.096876
A10: 45200 | B10: =_xll.PBF($C$1,"Total Revenue","TTM",$A10,"","USD","",$A10) -> 15419000000 | C10: =_xll.PBF($C$1,"Net Debt","TTM",$A10,"","USD","",$A10) -> 7372000000 | D10: =_xll.PBF($C$1,"Adjusted EBITDA","TTM",$A10,"","USD","",$A10) -> 3276000000 | E10: =_xll.PBF($C$1,"Adjusted EBITDA","NTM",$A10,"","USD","",$A10) -> 3276000000 | F10: =_xll.PBF($C$1,"Diluted EPS (Analyst Normalized)","NTM",$A10,"","USD","",$A10) -> 1.05 | G10: =_xll.PBF($C$1,"Diluted Weighted Average Shares Outstanding","TTM",$A10,"","USD","",$A10) -> 1832986280 | H10: {=_xlfn.LET( _xlpm.data, _xlfn.STOCKHISTORY("KVUE",$A10-10,$A10,0,0,0,1), INDEX(_xlpm.data,ROWS(_xlpm.data),0) )} -> 45198 | I10: 20.08 | J10: =I10/F10 -> 19.12381 | K10: =(I10*G10)+C10 -> 4.4178365e+10 | L10: =K10/D10 -> 13.485459
A11: 45231 | B11: =_xll.PBF($C$1,"Total Revenue","TTM",$A11,"","USD","",$A11) -> 15419000000 | C11: =_xll.PBF($C$1,"Net Debt","TTM",$A11,"","USD","",$A11) -> 7372000000 | D11: =_xll.PBF($C$1,"Adjusted EBITDA","TTM",$A11,"","USD","",$A11) -> 3276000000 | E11: =_xll.PBF($C$1,"Adjusted EBITDA","NTM",$A11,"","USD","",$A11) -> 3276000000 | F11: =_xll.PBF($C$1,"Diluted EPS (Analyst Normalized)","NTM",$A11,"","USD","",$A11) -> 1.05 | G11: =_xll.PBF($C$1,"Diluted Weighted Average Shares Outstanding","TTM",$A11,"","USD","",$A11) -> 1832986280 | H11: {=_xlfn.LET( _xlpm.data, _xlfn.STOCKHISTORY("KVUE",$A11-10,$A11,0,0,0,1), INDEX(_xlpm.data,ROWS(_xlpm.data),0) )} -> 45231 | I11: 18.88 | J11: =I11/F11 -> 17.980952 | K11: =(I11*G11)+C11 -> 4.1978781e+10 | L11: =K11/D11 -> 12.814036
A12: 45261 | B12: =_xll.PBF($C$1,"Total Revenue","TTM",$A12,"","USD","",$A12) -> 15545000000 | C12: =_xll.PBF($C$1,"Net Debt","TTM",$A12,"","USD","",$A12) -> 7288000000 | D12: =_xll.PBF($C$1,"Adjusted EBITDA","TTM",$A12,"","USD","",$A12) -> 3201000000 | E12: =_xll.PBF($C$1,"Adjusted EBITDA","NTM",$A12,"","USD","",$A12) -> 3201000000 | F12: =_xll.PBF($C$1,"Diluted EPS (Analyst Normalized)","NTM",$A12,"","USD","",$A12) -> 0.94 | G12: =_xll.PBF($C$1,"Diluted Weighted Average Shares Outstanding","TTM",$A12,"","USD","",$A12) -> 1842493140 | H12: {=_xlfn.LET( _xlpm.data, _xlfn.STOCKHISTORY("KVUE",$A12-10,$A12,0,0,0,1), INDEX(_xlpm.data,ROWS(_xlpm.data),0) )} -> 45261 | I12: 20.69 | J12: =I12/F12 -> 22.010638 | K12: =(I12*G12)+C12 -> 4.5409183e+10 | L12: =K12/D12 -> 14.185937
A13: 45292 | B13: =_xll.PBF($C$1,"Total Revenue","TTM",$A13,"","USD","",$A13) -> 15545000000 | C13: =_xll.PBF($C$1,"Net Debt","TTM",$A13,"","USD","",$A13) -> 7288000000 | D13: =_xll.PBF($C$1,"Adjusted EBITDA","TTM",$A13,"","USD","",$A13) -> 3201000000 | E13: =_xll.PBF($C$1,"Adjusted EBITDA","NTM",$A13,"","USD","",$A13) -> 3201000000 | F13: =_xll.PBF($C$1,"Diluted EPS (Analyst Normalized)","NTM",$A13,"","USD","",$A13) -> 0.94 | G13: =_xll.PBF($C$1,"Diluted Weighted Average Shares Outstanding","TTM",$A13,"","USD","",$A13) -> 1842493140 | H13: {=_xlfn.LET( _xlpm.data, _xlfn.STOCKHISTORY("KVUE",$A13-10,$A13,0,0,0,1), INDEX(_xlpm.data,ROWS(_xlpm.data),0) )} -> 45289 | I13: 21.53 | J13: =I13/F13 -> 22.904255 | K13: =(I13*G13)+C13 -> 4.6956877e+10 | L13: =K13/D13 -> 14.66944
A14: 45323 | B14: =_xll.PBF($C$1,"Total Revenue","TTM",$A14,"","USD","",$A14) -> 15545000000 | C14: =_xll.PBF($C$1,"Net Debt","TTM",$A14,"","USD","",$A14) -> 7288000000 | D14: =_xll.PBF($C$1,"Adjusted EBITDA","TTM",$A14,"","USD","",$A14) -> 3201000000 | E14: =_xll.PBF($C$1,"Adjusted EBITDA","NTM",$A14,"","USD","",$A14) -> 3201000000 | F14: =_xll.PBF($C$1,"Diluted EPS (Analyst Normalized)","NTM",$A14,"","USD","",$A14) -> 0.94 | G14: =_xll.PBF($C$1,"Diluted Weighted Average Shares Outstanding","TTM",$A14,"","USD","",$A14) -> 1842493140 | H14: {=_xlfn.LET( _xlpm.data, _xlfn.STOCKHISTORY("KVUE",$A14-10,$A14,0,0,0,1), INDEX(_xlpm.data,ROWS(_xlpm.data),0) )} -> 45323 | I14: 20.89 | J14: =I14/F14 -> 22.223404 | K14: =(I14*G14)+C14 -> 4.5777682e+10 | L14: =K14/D14 -> 14.301056
A15: 45352 | B15: =_xll.PBF($C$1,"Total Revenue","TTM",$A15,"","USD","",$A15) -> 15444000000 | C15: =_xll.PBF($C$1,"Net Debt","TTM",$A15,"","USD","",$A15) -> 7045000000 | D15: =_xll.PBF($C$1,"Adjusted EBITDA","TTM",$A15,"","USD","",$A15) -> 3236000000 | E15: =_xll.PBF($C$1,"Adjusted EBITDA","NTM",$A15,"","USD","",$A15) -> 3236000000 | F15: =_xll.PBF($C$1,"Diluted EPS (Analyst Normalized)","NTM",$A15,"","USD","",$A15) -> 0.9 | G15: =_xll.PBF($C$1,"Diluted Weighted Average Shares Outstanding","TTM",$A15,"","USD","",$A15) -> 1850000000 | H15: {=_xlfn.LET( _xlpm.data, _xlfn.STOCKHISTORY("KVUE",$A15-10,$A15,0,0,0,1), INDEX(_xlpm.data,ROWS(_xlpm.data),0) )} -> 45352 | I15: 18.82 | J15: =I15/F15 -> 20.911111 | K15: =(I15*G15)+C15 -> 41862000000 | L15: =K15/D15 -> 12.936341
A16: 45383 | B16: =_xll.PBF($C$1,"Total Revenue","TTM",$A16,"","USD","",$A16) -> 15444000000 | C16: =_xll.PBF($C$1,"Net Debt","TTM",$A16,"","USD","",$A16) -> 7045000000 | D16: =_xll.PBF($C$1,"Adjusted EBITDA","TTM",$A16,"","USD","",$A16) -> 3236000000 | E16: =_xll.PBF($C$1,"Adjusted EBITDA","NTM",$A16,"","USD","",$A16) -> 3236000000 | F16: =_xll.PBF($C$1,"Diluted EPS (Analyst Normalized)","NTM",$A16,"","USD","",$A16) -> 0.9 | G16: =_xll.PBF($C$1,"Diluted Weighted Average Shares Outstanding","TTM",$A16,"","USD","",$A16) -> 1850000000 | H16: {=_xlfn.LET( _xlpm.data, _xlfn.STOCKHISTORY("KVUE",$A16-10,$A16,0,0,0,1), INDEX(_xlpm.data,ROWS(_xlpm.data),0) )} -> 45383 | I16: 21.23 | J16: =I16/F16 -> 23.588889 | K16: =(I16*G16)+C16 -> 46320500000 | L16: =K16/D16 -> 14.314122
A17: 45413 | B17: =_xll.PBF($C$1,"Total Revenue","TTM",$A17,"","USD","",$A17) -> 15444000000 | C17: =_xll.PBF($C$1,"Net Debt","TTM",$A17,"","USD","",$A17) -> 7045000000 | D17: =_xll.PBF($C$1,"Adjusted EBITDA","TTM",$A17,"","USD","",$A17) -> 3236000000 | E17: =_xll.PBF($C$1,"Adjusted EBITDA","NTM",$A17,"","USD","",$A17) -> 3236000000 | F17: =_xll.PBF($C$1,"Diluted EPS (Analyst Normalized)","NTM",$A17,"","USD","",$A17) -> 0.9 | G17: =_xll.PBF($C$1,"Diluted Weighted Average Shares Outstanding","TTM",$A17,"","USD","",$A17) -> 1850000000 | H17: {=_xlfn.LET( _xlpm.data, _xlfn.STOCKHISTORY("KVUE",$A17-10,$A17,0,0,0,1), INDEX(_xlpm.data,ROWS(_xlpm.data),0) )} -> 45413 | I17: 18.85 | J17: =I17/F17 -> 20.944444 | K17: =(I17*G17)+C17 -> 41917500000 | L17: =K17/D17 -> 12.953492
... A40: 46113 | B40: =_xll.PBF($C$1,"Total Revenue","TTM",$A40,"","USD","",$A40) -> 15124000000 | C40: =_xll.PBF($C$1,"Net Debt","TTM",$A40,"","USD","",$A40) -> 7612000000 | D40: =_xll.PBF($C$1,"Adjusted EBITDA","TTM",$A40,"","USD","",$A40) -> 3437000000 | E40: =_xll.PBF($C$1,"Adjusted EBITDA","NTM",$A40,"","USD","",$A40) -> 3437000000 | F40: =_xll.PBF($C$1,"Diluted EPS (Analyst Normalized)","NTM",$A40,"","USD","",$A40) -> 0.77 | G40: =_xll.PBF($C$1,"Diluted Weighted Average Shares Outstanding","TTM",$A40,"","USD","",$A40) -> 1924000000 | H40: {=_xlfn.LET( _xlpm.data, _xlfn.STOCKHISTORY("KVUE",$A40-10,$A40,0,0,0,1), INDEX(_xlpm.data,ROWS(_xlpm.data),0) )} -> 46113 | I40: 17.38 | J40: =I40/F40 -> 22.571429 | K40: =(I40*G40)+C40 -> 41051120000 | L40: =K40/D40 -> 11.943881

Sheet IPO_2023_05_04
A1: Snapshot Date | B1: 2023-05-04
A2: Use same date for Date + Effective Date in all formulas
A4: Identifier | B4: Company | C4: Revenue TTM | D4: Shares Outstanding | E4: Net Debt | F4: EBITDA TTM | G4: EBITDA NTM | H4: Diluted EPS | I4: Market Cap | J4: Enterprise Value | K4: EV/LTM | L4: EV/NTM | M4: P/NTM
A5: NYS:KVUE | B5: Kenvue | C5: =_xll.PBF(A5,"Total Revenue","TTM",$B$1,"","USD","",$B$1) -> 14950000000 | D5: =_xll.PBF(A5,"Diluted Weighted Average Shares Outstanding","TTM",$B$1,"","USD","",$B$1) -> 1888972560 | E5: =_xll.PBF(A5,"Net Debt","TTM",$B$1,"","USD","",$B$1) -> -1115000000 | F5: =_xll.PBF(A5,"Adjusted EBITDA","TTM",$B$1,"","USD","",$B$1) -> 3606000000 | G5: =_xll.PBF(A5,"Adjusted EBITDA","NTM",$B$1,"","USD","",$B$1) -> 3606000000 | H5: =_xll.PBF(A5,"Diluted EPS (Analyst Normalized)","NTM",$B$1,"","USD","",$B$1) -> 0.93 | I5: =D16*D5 -> 50813361864 | J5: =I5+E5 -> 49698361864 | K5: =IFERROR(J5/F5,"") -> 13.78213 | L5: =IFERROR(J5/G5,"") -> 13.78213 | M5: =I5/(D5*H5) -> 28.924731
A6: NYS:PG | B6: Procter & Gamble | C6: =_xll.PBF(A6,"Total Revenue","TTM",$B$1,"","USD","",$B$1) -> 80968000000 | D6: =_xll.PBF(A6,"Diluted Weighted Average Shares Outstanding","TTM",$B$1,"","USD","",$B$1) -> 2495300000 | E6: =_xll.PBF(A6,"Net Debt","TTM",$B$1,"","USD","",$B$1) -> 28995000000 | F6: =_xll.PBF(A6,"Adjusted EBITDA","TTM",$B$1,"","USD","",$B$1) -> 21450000000 | G6: =_xll.PBF(A6,"Adjusted EBITDA","NTM",$B$1,"","USD","",$B$1) -> 21450000000 | H6: =_xll.PBF(A6,"Diluted EPS (Analyst Normalized)","NTM",$B$1,"","USD","",$B$1) -> 5.74 | I6: =D17*D6 -> 388044103000 | J6: =I6+E6 -> 417039103000 | K6: =IFERROR(J6/F6,"") -> 19.442382 | L6: =IFERROR(J6/G6,"") -> 19.442382 | M6: =I6/(D6*H6) -> 27.092334
A7: NAS:KMB | B7: Kimberly-Clark | C7: =_xll.PBF(A7,"Total Revenue","TTM",$B$1,"","USD","",$B$1) -> 20275000000 | D7: =_xll.PBF(A7,"Diluted Weighted Average Shares Outstanding","TTM",$B$1,"","USD","",$B$1) -> 338400000 | E7: =_xll.PBF(A7,"Net Debt","TTM",$B$1,"","USD","",$B$1) -> 7957000000 | F7: =_xll.PBF(A7,"Adjusted EBITDA","TTM",$B$1,"","USD","",$B$1) -> 3624000000 | G7: =_xll.PBF(A7,"Adjusted EBITDA","NTM",$B$1,"","USD","",$B$1) -> 3624000000 | H7: =_xll.PBF(A7,"Diluted EPS (Analyst Normalized)","NTM",$B$1,"","USD","",$B$1) -> 5.84 | I7: =D18*D7 -> 48868344000 | J7: =I7+E7 -> 56825344000 | K7: =IFERROR(J7/F7,"") -> 15.680283 | L7: =IFERROR(J7/G7,"") -> 15.680283 | M7: =I7/(D7*H7) -> 24.72774
A8: NYS:CL | B8: Colgate-Palmolive | C8: =_xll.PBF(A8,"Total Revenue","TTM",$B$1,"","USD","",$B$1) -> 18338000000 | D8: =_xll.PBF(A8,"Diluted Weighted Average Shares Outstanding","TTM",$B$1,"","USD","",$B$1) -> 836125000 | E8: =_xll.PBF(A8,"Net Debt","TTM",$B$1,"","USD","",$B$1) -> 8040000000 | F8: =_xll.PBF(A8,"Adjusted EBITDA","TTM",$B$1,"","USD","",$B$1) -> 3944000000 | G8: =_xll.PBF(A8,"Adjusted EBITDA","NTM",$B$1,"","USD","",$B$1) -> 3944000000 | H8: =_xll.PBF(A8,"Diluted EPS (Analyst Normalized)","NTM",$B$1,"","USD","",$B$1) -> 1.92 | I8: =D19*D8 -> 6.7550539e+10 | J8: =I8+E8 -> 75590538750 | K8: =IFERROR(J8/F8,"") -> 19.165958 | L8: =IFERROR(J8/G8,"") -> 19.165958 | M8: =I8/(D8*H8) -> 42.078125
A9: NYS:CHD | B9: Church & Dwight | C9: =_xll.PBF(A9,"Total Revenue","TTM",$B$1,"","USD","",$B$1) -> 5508200000 | D9: =_xll.PBF(A9,"Diluted Weighted Average Shares Outstanding","TTM",$B$1,"","USD","",$B$1) -> 246325000 | E9: =_xll.PBF(A9,"Net Debt","TTM",$B$1,"","USD","",$B$1) -> 2216000000 | F9: =_xll.PBF(A9,"Adjusted EBITDA","TTM",$B$1,"","USD","",$B$1) -> 1310300000 | G9: =_xll.PBF(A9,"Adjusted EBITDA","NTM",$B$1,"","USD","",$B$1) -> 1310300000 | H9: =_xll.PBF(A9,"Diluted EPS (Analyst Normalized)","NTM",$B$1,"","USD","",$B$1) -> 1.67 | I9: =D20*D9 -> 24056099500 | J9: =I9+E9 -> 26272099500 | K9: =IFERROR(J9/F9,"") -> 20.050446 | L9: =IFERROR(J9/G9,"") -> 20.050446 | M9: =I9/(D9*H9) -> 58.479042
A10: NYS:ABT | B10: Abbott Laboratories | C10: =_xll.PBF(A10,"Total Revenue","TTM",$B$1,"","USD","",$B$1) -> 41505000000 | D10: =_xll.PBF(A10,"Diluted Weighted Average Shares Outstanding","TTM",$B$1,"","USD","",$B$1) -> 1758293250 | E10: =_xll.PBF(A10,"Net Debt","TTM",$B$1,"","USD","",$B$1) -> 7368000000 | F10: =_xll.PBF(A10,"Adjusted EBITDA","TTM",$B$1,"","USD","",$B$1) -> 11213000000 | G10: =_xll.PBF(A10,"Adjusted EBITDA","NTM",$B$1,"","USD","",$B$1) -> 11213000000 | H10: =_xll.PBF(A10,"Diluted EPS (Analyst Normalized)","NTM",$B$1,"","USD","",$B$1) -> 3.29 | I10: =_xll.PBF(A10,"Market Cap","TTM",$B$1,"","USD","",$B$1) -> 192779642137 | J10: =I10+E10 -> 200147642137 | K10: =IFERROR(J10/F10,"") -> 17.849607 | L10: =IFERROR(J10/G10,"") -> 17.849607 | M10: =I10/(D10*H10) -> 33.325292
A11: NYS:COTY | B11: Coty | C11: =_xll.PBF(A11,"Total Revenue","TTM",$B$1,"","USD","",$B$1) -> 5268100000 | D11: =_xll.PBF(A11,"Diluted Weighted Average Shares Outstanding","TTM",$B$1,"","USD","",$B$1) -> 868800000 | E11: =_xll.PBF(A11,"Net Debt","TTM",$B$1,"","USD","",$B$1) -> 4127500000 | F11: =_xll.PBF(A11,"Adjusted EBITDA","TTM",$B$1,"","USD","",$B$1) -> 940400000 | G11: =_xll.PBF(A11,"Adjusted EBITDA","NTM",$B$1,"","USD","",$B$1) -> 940400000 | H11: =_xll.PBF(A11,"Diluted EPS (Analyst Normalized)","NTM",$B$1,"","USD","",$B$1) -> 0.14 | I11: =_xll.PBF(A11,"Market Cap","TTM",$B$1,"","USD","",$B$1) -> 9949793231 | J11: =I11+E11 -> 14077293231 | K11: =IFERROR(J11/F11,"") -> 14.969474 | L11: =IFERROR(J11/G11,"") -> 14.969474 | M11: =I11/(D11*H11) -> 81.802431
A12: NYS:EPC | B12: Edgewell Personal Care | C12: =_xll.PBF(A12,"Total Revenue","TTM",$B$1,"","USD","",$B$1) -> 2177500000 | D12: =_xll.PBF(A12,"Diluted Weighted Average Shares Outstanding","TTM",$B$1,"","USD","",$B$1) -> 52825000 | E12: =_xll.PBF(A12,"Net Debt","TTM",$B$1,"","USD","",$B$1) -> 1383500000 | F12: =_xll.PBF(A12,"Adjusted EBITDA","TTM",$B$1,"","USD","",$B$1) -> 330000000 | G12: =_xll.PBF(A12,"Adjusted EBITDA","NTM",$B$1,"","USD","",$B$1) -> 330000000 | H12: =_xll.PBF(A12,"Diluted EPS (Analyst Normalized)","NTM",$B$1,"","USD","",$B$1) -> 1.88 | I12: =_xll.PBF(A12,"Market Cap","TTM",$B$1,"","USD","",$B$1) -> 2221222392 | J12: =I12+E12 -> 3604722392 | K12: =IFERROR(J12/F12,"") -> 10.923401 | L12: =IFERROR(J12/G12,"") -> 10.923401 | M12: =I12/(D12*H12) -> 22.366328
D16: {=_xlfn.STOCKHISTORY("KVUE",$B$1,$B$1,0,0,1)} -> 26.9
D17: {=_xlfn.STOCKHISTORY("PG",$B$1,$B$1,0,0,1)} -> 155.51
D18: {=_xlfn.STOCKHISTORY("KMB",$B$1,$B$1,0,0,1)} -> 144.41
D19: {=_xlfn.STOCKHISTORY("CL",$B$1,$B$1,0,0,1)} -> 80.79
D20: {=_xlfn.STOCKHISTORY("CHD",$B$1,$B$1,0,0,1)} -> 97.66

Sheet Post1Y_2024_05_04
A1: Snapshot Date | B1: 2024-05-04
A2: Use same date for Date + Effective Date in all formulas
A4: Identifier | B4: Company | C4: Revenue TTM | D4: Shares Outstanding | E4: Net Debt | F4: EBITDA TTM | G4: EBITDA NTM | H4: Diluted EPS (Analyst Normalized) | I4: Market Cap | J4: Enterprise Value | K4: EV/LTM | L4: EV/NTM | M4: P/NTM
A5: NYS:KVUE | B5: Kenvue | C5: =_xll.PBF(A5,"Total Revenue","TTM",$B$1,"","USD","",$B$1) -> 15444000000 | D5: =_xll.PBF(A5,"Diluted Weighted Average Shares Outstanding","TTM",$B$1,"","USD","",$B$1) -> 1850000000 | E5: =_xll.PBF(A5,"Net Debt","TTM",$B$1,"","USD","",$B$1) -> 7045000000 | F5: =_xll.PBF(A5," Adjusted EBITDA","TTM",$B$1,"","USD","",$B$1) -> 3236000000 | G5: =_xll.PBF(A5,"Adjusted EBITDA","NTM",$B$1,"","USD","",$B$1) -> 3236000000 | H5: =_xll.PBF(A5,"Diluted EPS (Analyst Normalized)","NTM",$B$1,"","USD","",$B$1) -> 0.9 | I5: =D16*D5 -> 35520000000 | J5: =I5+E5 -> 42565000000 | K5: =IFERROR(J5/F5,"") -> 13.153585 | L5: =IFERROR(J5/G5,"") -> 13.153585 | M5: =I5/(D5*H5) -> 21.333333
A6: NYS:PG | B6: Procter & Gamble | C6: =_xll.PBF(A6,"Total Revenue","TTM",$B$1,"","USD","",$B$1) -> 84060000000 | D6: =_xll.PBF(A6,"Diluted Weighted Average Shares Outstanding","TTM",$B$1,"","USD","",$B$1) -> 2473250000 | E6: =_xll.PBF(A6,"Net Debt","TTM",$B$1,"","USD","",$B$1) -> 25154000000 | F6: =_xll.PBF(A6," Adjusted EBITDA","TTM",$B$1,"","USD","",$B$1) -> 24254000000 | G6: =_xll.PBF(A6,"Adjusted EBITDA","NTM",$B$1,"","USD","",$B$1) -> 24254000000 | H6: =_xll.PBF(A6,"Diluted EPS (Analyst Normalized)","NTM",$B$1,"","USD","",$B$1) -> 6.12 | I6: =D17*D6 -> 406750695000 | J6: =I6+E6 -> 431904695000 | K6: =IFERROR(J6/F6,"") -> 17.807566 | L6: =IFERROR(J6/G6,"") -> 17.807566 | M6: =I6/(D6*H6) -> 26.872549
A7: NAS:KMB | B7: Kimberly-Clark | C7: =_xll.PBF(A7,"Total Revenue","TTM",$B$1,"","USD","",$B$1) -> 17100000000 | D7: =_xll.PBF(A7,"Diluted Weighted Average Shares Outstanding","TTM",$B$1,"","USD","",$B$1) -> 338725000 | E7: =_xll.PBF(A7,"Net Debt","TTM",$B$1,"","USD","",$B$1) -> 7117000000 | F7: =_xll.PBF(A7," Adjusted EBITDA","TTM",$B$1,"","USD","",$B$1) -> 3413000000 | G7: =_xll.PBF(A7,"Adjusted EBITDA","NTM",$B$1,"","USD","",$B$1) -> 3413000000 | H7: =_xll.PBF(A7,"Diluted EPS (Analyst Normalized)","NTM",$B$1,"","USD","",$B$1) -> 5.44 | I7: =D18*D7 -> 46097085250 | J7: =I7+E7 -> 53214085250 | K7: =IFERROR(J7/F7,"") -> 15.591587 | L7: =IFERROR(J7/G7,"") -> 15.591587 | M7: =I7/(D7*H7) -> 25.016544
A8: NYS:CL | B8: Colgate-Palmolive | C8: =_xll.PBF(A8,"Total Revenue","TTM",$B$1,"","USD","",$B$1) -> 19752000000 | D8: =_xll.PBF(A8,"Diluted Weighted Average Shares Outstanding","TTM",$B$1,"","USD","",$B$1) -> 827425000 | E8: =_xll.PBF(A8,"Net Debt","TTM",$B$1,"","USD","",$B$1) -> 7610000000 | F8: =_xll.PBF(A8," Adjusted EBITDA","TTM",$B$1,"","USD","",$B$1) -> 4775000000 | G8: =_xll.PBF(A8,"Adjusted EBITDA","NTM",$B$1,"","USD","",$B$1) -> 4775000000 | H8: =_xll.PBF(A8,"Diluted EPS (Analyst Normalized)","NTM",$B$1,"","USD","",$B$1) -> 3.16 | I8: =D19*D8 -> 76851234000 | J8: =I8+E8 -> 84461234000 | K8: =IFERROR(J8/F8,"") -> 17.688217 | L8: =IFERROR(J8/G8,"") -> 17.688217 | M8: =I8/(D8*H8) -> 29.392405
A9: NYS:CHD | B9: Church & Dwight | C9: =_xll.PBF(A9,"Total Revenue","TTM",$B$1,"","USD","",$B$1) -> 5941400000 | D9: =_xll.PBF(A9,"Diluted Weighted Average Shares Outstanding","TTM",$B$1,"","USD","",$B$1) -> 247425000 | E9: =_xll.PBF(A9,"Net Debt","TTM",$B$1,"","USD","",$B$1) -> 1857100000 | F9: =_xll.PBF(A9," Adjusted EBITDA","TTM",$B$1,"","USD","",$B$1) -> 1370700000 | G9: =_xll.PBF(A9,"Adjusted EBITDA","NTM",$B$1,"","USD","",$B$1) -> 1370700000 | H9: =_xll.PBF(A9,"Diluted EPS (Analyst Normalized)","NTM",$B$1,"","USD","",$B$1) -> 3.15 | I9: =D20*D9 -> 26254266750 | J9: =I9+E9 -> 28111366750 | K9: =IFERROR(J9/F9,"") -> 20.508767 | L9: =IFERROR(J9/G9,"") -> 20.508767 | M9: =I9/(D9*H9) -> 33.685714
A10: NYS:ABT | B10: Abbott Laboratories | C10: =_xll.PBF(A10,"Total Revenue","TTM",$B$1,"","USD","",$B$1) -> 40326000000 | D10: =_xll.PBF(A10,"Diluted Weighted Average Shares Outstanding","TTM",$B$1,"","USD","",$B$1) -> 1748484250 | E10: =_xll.PBF(A10,"Net Debt","TTM",$B$1,"","USD","",$B$1) -> 7935000000 | F10: =_xll.PBF(A10," Adjusted EBITDA","TTM",$B$1,"","USD","",$B$1) -> 10708000000 | G10: =_xll.PBF(A10,"Adjusted EBITDA","NTM",$B$1,"","USD","",$B$1) -> 10708000000 | H10: =_xll.PBF(A10,"Diluted EPS (Analyst Normalized)","NTM",$B$1,"","USD","",$B$1) -> 3.21 | I10: =_xll.PBF(A10,"Market Cap","TTM",$B$1,"","USD","",$B$1) -> 184227215078 | J10: =I10+E10 -> 192162215078 | K10: =IFERROR(J10/F10,"") -> 17.945668 | L10: =IFERROR(J10/G10,"") -> 17.945668 | M10: =I10/(D10*H10) -> 32.823662
A11: NYS:COTY | B11: Coty | C11: =_xll.PBF(A11,"Total Revenue","TTM",$B$1,"","USD","",$B$1) -> 6009500000 | D11: =_xll.PBF(A11,"Diluted Weighted Average Shares Outstanding","TTM",$B$1,"","USD","",$B$1) -> 885900000 | E11: =_xll.PBF(A11,"Net Debt","TTM",$B$1,"","USD","",$B$1) -> 3554900000 | F11: =_xll.PBF(A11," Adjusted EBITDA","TTM",$B$1,"","USD","",$B$1) -> 1061400000 | G11: =_xll.PBF(A11,"Adjusted EBITDA","NTM",$B$1,"","USD","",$B$1) -> 1061400000 | H11: =_xll.PBF(A11,"Diluted EPS (Analyst Normalized)","NTM",$B$1,"","USD","",$B$1) -> 0.35 | I11: =_xll.PBF(A11,"Market Cap","TTM",$B$1,"","USD","",$B$1) -> 10383959031 | J11: =I11+E11 -> 13938859031 | K11: =IFERROR(J11/F11,"") -> 13.132522 | L11: =IFERROR(J11/G11,"") -> 13.132522 | M11: =I11/(D11*H11) -> 33.48962
A12: NYS:EPC | B12: Edgewell Personal Care | C12: =_xll.PBF(A12,"Total Revenue","TTM",$B$1,"","USD","",$B$1) -> 2271400000 | D12: =_xll.PBF(A12,"Diluted Weighted Average Shares Outstanding","TTM",$B$1,"","USD","",$B$1) -> 51450000 | E12: =_xll.PBF(A12,"Net Debt","TTM",$B$1,"","USD","",$B$1) -> 1262300000 | F12: =_xll.PBF(A12," Adjusted EBITDA","TTM",$B$1,"","USD","",$B$1) -> 334900000 | G12: =_xll.PBF(A12,"Adjusted EBITDA","NTM",$B$1,"","USD","",$B$1) -> 334900000 | H12: =_xll.PBF(A12,"Diluted EPS (Analyst Normalized)","NTM",$B$1,"","USD","",$B$1) -> 2.06 | I12: =_xll.PBF(A12,"Market Cap","TTM",$B$1,"","USD","",$B$1) -> 1888470485 | J12: =I12+E12 -> 3150770485 | K12: =IFERROR(J12/F12,"") -> 9.4080934 | L12: =IFERROR(J12/G12,"") -> 9.4080934 | M12: =I12/(D12*H12) -> 17.817945
D16: {=_xlfn.STOCKHISTORY("KVUE",$B$1-1,$B$1,0,0,1)} -> 19.2
D17: {=_xlfn.STOCKHISTORY("PG",$B$1-1,$B$1,0,0,1)} -> 164.46
D18: {=_xlfn.STOCKHISTORY("KMB",$B$1-1,$B$1,0,0,1)} -> 136.09
D19: {=_xlfn.STOCKHISTORY("CL",$B$1-1,$B$1,0,0,1)} -> 92.88
D20: {=_xlfn.STOCKHISTORY("CHD",$B$1-1,$B$1,0,0,1)} -> 106.11

Sheet PreDeal_2025_10_31
A1: Snapshot Date | B1: 2025-10-31
A2: Use same date for Date + Effective Date in all formulas
A4: Identifier | B4: Company | C4: Revenue TTM | D4: Shares Outstanding | E4: Net Debt | F4: EBITDA TTM | G4: EBITDA NTM | H4: Diluted EPS (Analyst Normalized) | I4: Market Cap | J4: Enterprise Value | K4: EV/LTM | L4: EV/NTM | M4: P/NTM
A5: NYS:KVUE | B5: Kenvue | C5: =_xll.PBF(A5,"Total Revenue","TTM",$B$1,"","USD","",$B$1) -> 15141000000 | D5: =_xll.PBF(A5,"Diluted Weighted Average Shares Outstanding","TTM",$B$1,"","USD","",$B$1) -> 1926500000 | E5: =_xll.PBF(A5,"Net Debt","TTM",$B$1,"","USD","",$B$1) -> 7674000000 | F5: =_xll.PBF(A5,"Adjusted EBITDA","TTM",$B$1,"","USD","",$B$1) -> 3371000000 | G5: =_xll.PBF(A5,"Adjusted EBITDA","NTM",$B$1,"","USD","",$B$1) -> 3371000000 | H5: =_xll.PBF(A5,"Diluted EPS (Analyst Normalized)","NTM",$B$1,"","USD","",$B$1) -> 0.74 | I5: =G15*D5 -> 27683805000 | J5: =I5+E5 -> 35357805000 | K5: =IFERROR(J5/F5,"") -> 10.488818 | L5: =IFERROR(J5/G5,"") -> 10.488818 | M5: =I5/(D5*H5) -> 19.418919
A6: NYS:PG | B6: Procter & Gamble | C6: =_xll.PBF(A6,"Total Revenue","TTM",$B$1,"","USD","",$B$1) -> 84933000000 | D6: =_xll.PBF(A6,"Diluted Weighted Average Shares Outstanding","TTM",$B$1,"","USD","",$B$1) -> 2447100000 | E6: =_xll.PBF(A6,"Net Debt","TTM",$B$1,"","USD","",$B$1) -> 24775000000 | F6: =_xll.PBF(A6,"Adjusted EBITDA","TTM",$B$1,"","USD","",$B$1) -> 24815000000 | G6: =_xll.PBF(A6,"Adjusted EBITDA","NTM",$B$1,"","USD","",$B$1) -> 24815000000 | H6: =_xll.PBF(A6,"Diluted EPS (Analyst Normalized)","NTM",$B$1,"","USD","",$B$1) -> 6.85 | I6: =G16*D6 -> 367970427000 | J6: =I6+E6 -> 392745427000 | K6: =IFERROR(J6/F6,"") -> 15.826936 | L6: =IFERROR(J6/G6,"") -> 15.826936 | M6: =I6/(D6*H6) -> 21.951825
A7: NAS:KMB | B7: Kimberly-Clark | C7: =_xll.PBF(A7,"Total Revenue","TTM",$B$1,"","USD","",$B$1) -> 16471000000 | D7: =_xll.PBF(A7,"Diluted Weighted Average Shares Outstanding","TTM",$B$1,"","USD","",$B$1) -> 333475000 | E7: =_xll.PBF(A7,"Net Debt","TTM",$B$1,"","USD","",$B$1) -> 6687000000 | F7: =_xll.PBF(A7,"Adjusted EBITDA","TTM",$B$1,"","USD","",$B$1) -> 3236000000 | G7: =_xll.PBF(A7,"Adjusted EBITDA","NTM",$B$1,"","USD","",$B$1) -> 3236000000 | H7: =_xll.PBF(A7,"Diluted EPS (Analyst Normalized)","NTM",$B$1,"","USD","",$B$1) -> 5.91 | I7: =G17*D7 -> 39920292250 | J7: =I7+E7 -> 46607292250 | K7: =IFERROR(J7/F7,"") -> 14.402748 | L7: =IFERROR(J7/G7,"") -> 14.402748 | M7: =I7/(D7*H7) -> 20.255499
A8: NYS:CL | B8: Colgate-Palmolive | C8: =_xll.PBF(A8,"Total Revenue","TTM",$B$1,"","USD","",$B$1) -> 20097000000 | D8: =_xll.PBF(A8,"Diluted Weighted Average Shares Outstanding","TTM",$B$1,"","USD","",$B$1) -> 814650000 | E8: =_xll.PBF(A8,"Net Debt","TTM",$B$1,"","USD","",$B$1) -> 7140000000 | F8: =_xll.PBF(A8,"Adjusted EBITDA","TTM",$B$1,"","USD","",$B$1) -> 4900000000 | G8: =_xll.PBF(A8,"Adjusted EBITDA","NTM",$B$1,"","USD","",$B$1) -> 4900000000 | H8: =_xll.PBF(A8,"Diluted EPS (Analyst Normalized)","NTM",$B$1,"","USD","",$B$1) -> 3.57 | I8: =G18*D8 -> 62768782500 | J8: =I8+E8 -> 69908782500 | K8: =IFERROR(J8/F8,"") -> 14.267098 | L8: =IFERROR(J8/G8,"") -> 14.267098 | M8: =I8/(D8*H8) -> 21.582633
A9: NYS:CHD | B9: Church & Dwight | C9: =_xll.PBF(A9,"Total Revenue","TTM",$B$1,"","USD","",$B$1) -> 6141000000 | D9: =_xll.PBF(A9,"Diluted Weighted Average Shares Outstanding","TTM",$B$1,"","USD","",$B$1) -> 246300000 | E9: =_xll.PBF(A9,"Net Debt","TTM",$B$1,"","USD","",$B$1) -> 1899200000 | F9: =_xll.PBF(A9,"Adjusted EBITDA","TTM",$B$1,"","USD","",$B$1) -> 1453500000 | G9: =_xll.PBF(A9,"Adjusted EBITDA","NTM",$B$1,"","USD","",$B$1) -> 1453500000 | H9: =_xll.PBF(A9,"Diluted EPS (Analyst Normalized)","NTM",$B$1,"","USD","",$B$1) -> 3.18 | I9: =G19*D9 -> 21598047000 | J9: =I9+E9 -> 23497247000 | K9: =IFERROR(J9/F9,"") -> 16.165977 | L9: =IFERROR(J9/G9,"") -> 16.165977 | M9: =I9/(D9*H9) -> 27.575472
A10: NYS:ABT | B10: Abbott Laboratories | C10: =_xll.PBF(A10,"Total Revenue","TTM",$B$1,"","USD","",$B$1) -> 43843000000 | D10: =_xll.PBF(A10,"Diluted Weighted Average Shares Outstanding","TTM",$B$1,"","USD","",$B$1) -> 1747795250 | E10: =_xll.PBF(A10,"Net Debt","TTM",$B$1,"","USD","",$B$1) -> 5208000000 | F10: =_xll.PBF(A10,"Adjusted EBITDA","TTM",$B$1,"","USD","",$B$1) -> 12119000000 | G10: =_xll.PBF(A10,"Adjusted EBITDA","NTM",$B$1,"","USD","",$B$1) -> 12119000000 | H10: =_xll.PBF(A10,"Diluted EPS (Analyst Normalized)","NTM",$B$1,"","USD","",$B$1) -> 7.98 | I10: =_xll.PBF(A10,"Market Cap","TTM",$B$1,"","USD","",$B$1) -> 214959350088 | J10: =I10+E10 -> 220167350088 | K10: =IFERROR(J10/F10,"") -> 18.167122 | L10: =IFERROR(J10/G10,"") -> 18.167122 | M10: =I10/(D10*H10) -> 15.412138
A11: NYS:COTY | B11: Coty | C11: =_xll.PBF(A11,"Total Revenue","TTM",$B$1,"","USD","",$B$1) -> 5892900000 | D11: =_xll.PBF(A11,"Diluted Weighted Average Shares Outstanding","TTM",$B$1,"","USD","",$B$1) -> 870900000 | E11: =_xll.PBF(A11,"Net Debt","TTM",$B$1,"","USD","",$B$1) -> 3988100000 | F11: =_xll.PBF(A11,"Adjusted EBITDA","TTM",$B$1,"","USD","",$B$1) -> 1081700000 | G11: =_xll.PBF(A11,"Adjusted EBITDA","NTM",$B$1,"","USD","",$B$1) -> 1081700000 | H11: =_xll.PBF(A11,"Diluted EPS (Analyst Normalized)","NTM",$B$1,"","USD","",$B$1) -> -0.44 | I11: =_xll.PBF(A11,"Market Cap","TTM",$B$1,"","USD","",$B$1) -> 3469214184 | J11: =I11+E11 -> 7457314184 | K11: =IFERROR(J11/F11,"") -> 6.8940688 | L11: =IFERROR(J11/G11,"") -> 6.8940688 | M11: =I11/(D11*H11) -> -9.0533674
A12: NYS:EPC | B12: Edgewell Personal Care | C12: =_xll.PBF(A12,"Total Revenue","TTM",$B$1,"","USD","",$B$1) -> 2203900000 | D12: =_xll.PBF(A12,"Diluted Weighted Average Shares Outstanding","TTM",$B$1,"","USD","",$B$1) -> 48375000 | E12: =_xll.PBF(A12,"Net Debt","TTM",$B$1,"","USD","",$B$1) -> 1212600000 | F12: =_xll.PBF(A12,"Adjusted EBITDA","TTM",$B$1,"","USD","",$B$1) -> 320500000 | G12: =_xll.PBF(A12,"Adjusted EBITDA","NTM",$B$1,"","USD","",$B$1) -> 320500000 | H12: =_xll.PBF(A12,"Diluted EPS (Analyst Normalized)","NTM",$B$1,"","USD","",$B$1) -> 1.35 | I12: =_xll.PBF(A12,"Market Cap","TTM",$B$1,"","USD","",$B$1) -> 900941691 | J12: =I12+E12 -> 2113541691 | K12: =IFERROR(J12/F12,"") -> 6.5945139 | L12: =IFERROR(J12/G12,"") -> 6.5945139 | M12: =I12/(D12*H12) -> 13.795643
G15: {=_xlfn.STOCKHISTORY("KVUE",$B$1,$B$1,0,0,1)} -> 14.37
G16: {=_xlfn.STOCKHISTORY("PG",$B$1,$B$1,0,0,1)} -> 150.37
G17: {=_xlfn.STOCKHISTORY("KMB",$B$1,$B$1,0,0,1)} -> 119.71
G18: {=_xlfn.STOCKHISTORY("CL",$B$1,$B$1,0,0,1)} -> 77.05
G19: {=_xlfn.STOCKHISTORY("CHD",$B$1,$B$1,0,0,1)} -> 87.69

Sheet Summary
A1: Company | B1: IPO EV/NTM | C1: 1Y EV/NTM | D1: Pre-Deal EV/NTM | E1: IPO P/E | F1: 1Y P/E | G1: Pre-Deal P/E
A2: Kenvue | B2: =IPO_2023_05_04!L5 -> 13.78213 | C2: =Post1Y_2024_05_04!L5 -> 13.153585 | D2: =PreDeal_2025_10_31!L5 -> 10.488818 | E2: =IPO_2023_05_04!M5 -> 28.924731 | F2: =Post1Y_2024_05_04!M5 -> 21.333333 | G2: =PreDeal_2025_10_31!M5 -> 19.418919
A3: Procter & Gamble | B3: =IPO_2023_05_04!L6 -> 19.442382 | C3: =Post1Y_2024_05_04!L6 -> 17.807566 | D3: =PreDeal_2025_10_31!L6 -> 15.826936 | E3: =IPO_2023_05_04!M6 -> 27.092334 | F3: =Post1Y_2024_05_04!M6 -> 26.872549 | G3: =PreDeal_2025_10_31!M6 -> 21.951825
A4: Kimberly-Clark | B4: =IPO_2023_05_04!L7 -> 15.680283 | C4: =Post1Y_2024_05_04!L7 -> 15.591587 | D4: =PreDeal_2025_10_31!L7 -> 14.402748 | E4: =IPO_2023_05_04!M7 -> 24.72774 | F4: =Post1Y_2024_05_04!M7 -> 25.016544 | G4: =PreDeal_2025_10_31!M7 -> 20.255499
A5: Colgate-Palmolive | B5: =IPO_2023_05_04!L8 -> 19.165958 | C5: =Post1Y_2024_05_04!L8 -> 17.688217 | D5: =PreDeal_2025_10_31!L8 -> 14.267098 | E5: =IPO_2023_05_04!M8 -> 42.078125 | F5: =Post1Y_2024_05_04!M8 -> 29.392405 | G5: =PreDeal_2025_10_31!M8 -> 21.582633
A6: Church & Dwight | B6: =IPO_2023_05_04!L9 -> 20.050446 | C6: =Post1Y_2024_05_04!L9 -> 20.508767 | D6: =PreDeal_2025_10_31!L9 -> 16.165977 | E6: =IPO_2023_05_04!M9 -> 58.479042 | F6: =Post1Y_2024_05_04!M9 -> 33.685714 | G6: =PreDeal_2025_10_31!M9 -> 27.575472
A7: Abbott Laboratories | B7: =IPO_2023_05_04!L10 -> 17.849607 | C7: =Post1Y_2024_05_04!L10 -> 17.945668 | D7: =PreDeal_2025_10_31!L10 -> 18.167122 | E7: =IPO_2023_05_04!M10 -> 33.325292 | F7: =Post1Y_2024_05_04!M10 -> 32.823662 | G7: =PreDeal_2025_10_31!M10 -> 15.412138
A8: Coty | B8: =IPO_2023_05_04!L11 -> 14.969474 | C8: =Post1Y_2024_05_04!L11 -> 13.132522 | D8: =PreDeal_2025_10_31!L11 -> 6.8940688 | E8: =IPO_2023_05_04!M11 -> 81.802431 | F8: =Post1Y_2024_05_04!M11 -> 33.48962 | G8: =PreDeal_2025_10_31!M11 -> -9.0533674
A9: Edgewell Personal Care | B9: =IPO_2023_05_04!L12 -> 10.923401 | C9: =Post1Y_2024_05_04!L12 -> 9.4080934 | D9: =PreDeal_2025_10_31!L12 -> 6.5945139 | E9: =IPO_2023_05_04!M12 -> 22.366328 | F9: =Post1Y_2024_05_04!M12 -> 17.817945 | G9: =PreDeal_2025_10_31!M12 -> 13.795643
A12: Metric | B12: IPO (All Comps) | C12: 1Y (All Comps) | D12: Pre-Deal (All Comps) | E12: IPO (Core Excl.) | F12: 1Y (Core Excl.) | G12: Pre-Deal (Core Excl.)
A13: Peer Median EV/NTM | B13: =AVERAGE(B3:B9) -> 16.868793 | C13: =AVERAGE(C3:C9) -> 16.011774 | D13: =AVERAGE(D3:D9) -> 13.188352 | E13: =MEDIAN(B3:B6) -> 19.30417 | F13: =MEDIAN(C3:C6) -> 17.747891 | G13: =MEDIAN(D3:D6) -> 15.114842
A14: KVUE EV/NTM | B14: =B2 -> 13.78213 | C14: =C2 -> 13.153585 | D14: =D2 -> 10.488818 | E14: =B2 -> 13.78213 | F14: =C2 -> 13.153585 | G14: =D2 -> 10.488818
A15: KVUE Discount to Median | B15: =IFERROR(B2/B13-1,"") -> -0.18298065 | C15: =IFERROR(C2/C13-1,"") -> -0.17850549 | D15: =IFERROR(D2/D13-1,"") -> -0.20469079 | E15: =IFERROR(B2/E13-1,"") -> -0.28605425 | F15: =IFERROR(C2/F13-1,"") -> -0.25886492 | G15: =IFERROR(D2/G13-1,"") -> -0.30605839
A17: Peer Median P/NTM | B17: =AVERAGE(E3:E9) -> 41.410185 | C17: =AVERAGE(F3:F9) -> 28.442634 | D17: =AVERAGE(G3:G9) -> 15.931406 | E17: =MEDIAN(E3:E6) -> 34.58523 | F17: =MEDIAN(F3:F6) -> 28.132477 | G17: =MEDIAN(G3:G6) -> 21.767229
A18: KVUE P/NTM | B18: =E2 -> 28.924731 | C18: =F2 -> 21.333333 | D18: =G2 -> 19.418919 | E18: =E2 -> 28.924731 | F18: =F2 -> 21.333333 | G18: =G2 -> 19.418919
A19: KVUE Discount to Median | B19: =IFERROR(E2/B17-1,"") -> -0.30150683 | C19: =IFERROR(F2/C17-1,"") -> -0.24995226 | D19: =IFERROR(G2/D17-1,"") -> 0.21890804 | E19: =IFERROR(E2/E17-1,"") -> -0.16366809 | F19: =IFERROR(F2/F17-1,"") -> -0.24168308 | G19: =IFERROR(G2/G17-1,"") -> -0.10788282
